Workbook

Sheet ✓ Controlli
A1: 🔍 AUDIT PIANO FINANZIARIO INTUR
A2: Controlli live — per il mese dopo: aggiorna saldi banche e cancella i mesi passati dai fogli dettaglio
A4: # | B4: ESITO | C4: CONTROLLO
A5: ERRORI
A6: 1 | B6: {=IF(SUMPRODUCT(ISERROR('Piano Finanziario'!C3:P46)*1)=0,"OK","ERRORE")} -> OK | C6: Zero errori nel Piano Finanziario
A7: 2 | B7: {=IF(SUMPRODUCT(ISERROR('Salari e Stipendi'!C3:S5)*1)+SUMPRODUCT(ISERROR(Utenze!C3:S61)*1)+SUMPRODUCT(ISERROR('Materie Prime-Conumo '!C3:S29)*1)+SUMPRODUCT(ISERROR('Tasse e Imposte'!C3:S59)*1)+SUMPRODUCT(ISERROR('Mutui e Finaziamenti'!C3:S62)*1)+SUMPRODUCT(ISERROR(Consulenze!C3:S62)*1)+SUMPRODUCT(ISERROR('Godimento Beni di Terzi'!C3:S62)*1)+SUMPRODUCT(ISERROR(' Varie ed Eventuali'!C3:S5)*1)+SUMPRODUCT(ISERROR('Canoni e servizi'!C3:S61)*1)=0,"OK","ERRORE")} -> OK | C7: Zero errori in tutti i fogli dettaglio
A9: ENTRATE
A10: 3 | B10: =IF(ABS('Piano Finanziario'!O12-SUM('Piano Finanziario'!D12:M12))<0.01,"OK","ERRORE") -> ERRORE | C10: Totale Entrate = somma mesi
A11: 4 | B11: =IF(ABS('Piano Finanziario'!O27-SUM('Piano Finanziario'!C14:M26))<0.01,"OK","ERRORE") -> ERRORE | C11: Totale Uscite = somma dettaglio
A12: 5 | B12: =IF(ABS('Piano Finanziario'!O29-('Piano Finanziario'!O12-'Piano Finanziario'!O27))<0.01,"OK","ERRORE") -> OK | C12: Cash Flow = Entrate - Uscite
A14: LINK FOGLI
A15: 6 | B15: {=IF(ABS(SUM('Piano Finanziario'!D14:M14)-SUMPRODUCT(('Salari e Stipendi'!D3:S3)*(COLUMN('Salari e Stipendi'!D3:S3)>=MATCH('Piano Finanziario'!D2,'Salari e Stipendi'!D2:S2,0)+3)))<0.01,"OK","ERRORE")} -> OK | C15: Salari e Stipendi: Piano = foglio
A16: 7 | B16: {=IF(ABS(SUM('Piano Finanziario'!D15:M15)-SUMPRODUCT((Utenze!D3:S3)*(COLUMN(Utenze!D3:S3)>=MATCH('Piano Finanziario'!D2,Utenze!D2:S2,0)+3)))<0.01,"OK","ERRORE")} -> OK | C16: Utenze: Piano = foglio
A17: 8 | B17: {=IF(ABS(SUM('Piano Finanziario'!D16:M16)-SUMPRODUCT(('Materie Prime-Conumo '!D3:S3)*(COLUMN('Materie Prime-Conumo '!D3:S3)>=MATCH('Piano Finanziario'!D2,'Materie Prime-Conumo '!D2:S2,0)+3)))<0.01,"OK","ERRORE")} -> OK | C17: Materie Prime: Piano = foglio
A18: 9 | B18: {=IF(ABS(SUM('Piano Finanziario'!D17:M17)-SUMPRODUCT(('Tasse e Imposte'!D3:S3)*(COLUMN('Tasse e Imposte'!D3:S3)>=MATCH('Piano Finanziario'!D2,'Tasse e Imposte'!D2:S2,0)+3)))<0.01,"OK","ERRORE")} -> OK | C18: Tasse e Imposte: Piano = foglio
A19: 10 | B19: {=IF(ABS(SUM('Piano Finanziario'!D18:M18)-SUMPRODUCT(('Mutui e Finaziamenti'!D3:S3)*(COLUMN('Mutui e Finaziamenti'!D3:S3)>=MATCH('Piano Finanziario'!D2,'Mutui e Finaziamenti'!D2:S2,0)+3)))<0.01,"OK","ERRORE")} -> OK | C19: Mutui e Finanziamenti: Piano = foglio
A20: 11 | B20: {=IF(ABS(SUM('Piano Finanziario'!D19:M19)-SUMPRODUCT((Consulenze!D3:S3)*(COLUMN(Consulenze!D3:S3)>=MATCH('Piano Finanziario'!D2,Consulenze!D2:S2,0)+3)))<0.01,"OK","ERRORE")} -> OK | C20: Consulenze: Piano = foglio
A21: 12 | B21: {=IF(ABS(SUM('Piano Finanziario'!D20:M20)-SUMPRODUCT(('Godimento Beni di Terzi'!D3:S3)*(COLUMN('Godimento Beni di Terzi'!D3:S3)>=MATCH('Piano Finanziario'!D2,'Godimento Beni di Terzi'!D2:S2,0)+3)))<0.01,"OK","ERRORE")} -> OK | C21: Godimento Beni di Terzi: Piano = foglio
A22: 13 | B22: {=IF(ABS(SUM('Piano Finanziario'!D21:M21)-SUMPRODUCT((' Varie ed Eventuali'!D3:S3)*(COLUMN(' Varie ed Eventuali'!D3:S3)>=MATCH('Piano Finanziario'!D2,' Varie ed Eventuali'!D2:S2,0)+3)))<0.01,"OK","ERRORE")} -> OK | C22: Varie ed Eventuali: Piano = foglio
A23: 14 | B23: {=IF(ABS(SUM('Piano Finanziario'!D22:M22)-SUMPRODUCT(('Canoni e servizi'!D3:S3)*(COLUMN('Canoni e servizi'!D3:S3)>=MATCH('Piano Finanziario'!D2,'Canoni e servizi'!D2:S2,0)+3)))<0.01,"OK","ERRORE")} -> OK | C23: Canoni e servizi: Piano = foglio
A25: SALDI
A26: 15 | B26: =IF(ABS('Piano Finanziario'!D3-'Piano Finanziario'!C35)<0.01,"OK","ERRORE") -> OK | C26: Saldo iniziale = Totale Banche
A27: 16 | B27: {=IF(SUMPRODUCT(ABS('Piano Finanziario'!D38:M38-('Piano Finanziario'!D3:M3+'Piano Finanziario'!D29:M29+'Piano Finanziario'!D35:M35)))<0.01,"OK","ERRORE")} -> OK | C27: Saldo Periodo = Prec + CF + Banche (ogni mese)
A28: 17 | B28: {=IF(SUMPRODUCT(ABS('Piano Finanziario'!D46:M46-('Piano Finanziario'!D38:M38+'Piano Finanziario'!D44:M44)))<0.01,"OK","ERRORE")} -> OK | C28: CF con Affidamenti = Saldo + Affidamenti
A30: FOGLI INTERNI
A31: 18 | B31: =IF(ABS('Salari e Stipendi'!C3-SUM('Salari e Stipendi'!D3:S3))<0.01,"OK","ERRORE") -> OK | C31: Salari: totale = somma mesi
A32: 19 | B32: =IF(ABS(Utenze!C3-SUM(Utenze!D3:S3))<0.01,"OK","ERRORE") -> OK | C32: Utenze: totale = somma mesi
A33: 20 | B33: =IF(ABS('Tasse e Imposte'!C3-SUM('Tasse e Imposte'!D3:S3))<0.01,"OK","ERRORE") -> OK | C33: Tasse: totale = somma mesi
A34: 21 | B34: =IF(ABS('Mutui e Finaziamenti'!C3-SUM('Mutui e Finaziamenti'!D3:S3))<0.01,"OK","ERRORE") -> OK | C34: Mutui: totale = somma mesi
A35: 22 | B35: =IF(ABS(Consulenze!C3-SUM(Consulenze!D3:S3))<0.01,"OK","ERRORE") -> OK | C35: Consulenze: totale = somma mesi
A36: 23 | B36: =IF(ABS(' Varie ed Eventuali'!C3-SUM(' Varie ed Eventuali'!D3:S3))+ABS('Canoni e servizi'!C3-SUM('Canoni e servizi'!D3:S3))+ABS('Godimento Beni di Terzi'!C3-SUM('Godimento Beni di Terzi'!D3:S3))+ABS('Materie Prime-Conumo '!C3-SUM('Materie Prime-Conumo '!D3:S3))<0.01,"OK","ERRORE") -> OK | C36: Varie + Canoni + Godimento + Mat.Prime: totale = somma
A38: ══════════════════════════════
B39: =IF(COUNTIF(B6:B36,"ERRORE")=0,"✓ TUTTI I CONTROLLI OK (×"&COUNTIF(B6:B36,"OK")&" verifiche)","✗ "&COUNTIF(B6:B36,"ERRORE")&" ERRORI su "&(COUNTIF(B6:B36,"OK")+COUNTIF(B6:B36,"ERRORE"))&" verifiche") -> ✗ 2 ERRORI su 23 verifiche

Sheet Piano Finanziario
A1: INTUR | C1: DATA RILEVAZ | D1: 2026 | N1: 2027
C2: 30/06/2026 | D2: MARZO | E2: APRILE | F2: MAGGIO | G2: GIUGNO | H2: LUGLIO | I2: AGOSTO | J2: SETTEMBRE | K2: OTTOBRE | L2: NOVEMBRE | M2: DICEMBRE | N2: GENNAIO | O2: FEBBRAIO | P2: MARZO | Q2: APRILE | R2: MAGGIO | S2: GIUGNO
A3: SALDO MESE PRECED. | D3: =C35 -> 189826.72 | E3: =D38 -> 189826.72 | F3: =E38 -> 189826.72 | G3: =F38 -> 189826.72 | H3: =G38 -> 189826.72 | I3: =H38 -> 520088.05 | J3: =I38 -> 727856.76 | K3: =J38 -> 720368.28 | L3: =K38 -> 677179.8 | ... S3: =R38 -> 573102.84
A5: Fitto Hotel | H5: 488000 | I5: 122000
A6: Fitto AR | I6: 60000
A7: Entrate Residence | D7: 0 | I7: 0 | J7: 0 | K7: 0 | L7: 0 | M7: 0
A8: Ribaltamento Costi a Orti
A9: Entrate Farmacia | H9: 3750 | I9: 3750 | J9: 3750 | K9: 3750 | L9: 3750 | M9: 3750
A10: Entrate Spiaggia | H10: 75000 | I10: 75000 | J10: 35000
A12: TOTALE ENTRATE | C12: =SUM(C5:C9) -> 0 | D12: =SUM(D5:D11) -> 0 | E12: =SUM(E5:E11) -> 0 | F12: =SUM(F5:F11) -> 0 | G12: =SUM(G5:G11) -> 0 | H12: =SUM(H5:H11) -> 566750 | I12: =SUM(I5:I11) -> 260750 | J12: =SUM(J5:J11) -> 38750 | K12: =SUM(K5:K11) -> 3750 | ... S12: =SUM(S5:S11) -> 0
A14: Salari e Stipendi | D14: ='Salari e Stipendi'!J3 -> 0 | E14: ='Salari e Stipendi'!K3 -> 0 | F14: ='Salari e Stipendi'!L3 -> 0 | G14: ='Salari e Stipendi'!M3 -> 0 | H14: ='Salari e Stipendi'!N3 -> 16000 | I14: ='Salari e Stipendi'!O3 -> 21000 | J14: ='Salari e Stipendi'!P3 -> 15000 | K14: ='Salari e Stipendi'!Q3 -> 14000 | ... S14: ='Salari e Stipendi'!Y3 -> 0
A15: Utenze | D15: =Utenze!J3 -> 0 | E15: =Utenze!K3 -> 0 | F15: =Utenze!L3 -> 0 | G15: =Utenze!M3 -> 0 | H15: =Utenze!N3 -> 19125.16 | I15: =Utenze!O3 -> 1338.16 | J15: =Utenze!P3 -> 850 | K15: =Utenze!Q3 -> 1250 | ... S15: =Utenze!Y3 -> 0
A16: Materie Prime/Consumo | D16: ='Materie Prime-Conumo '!J3 -> 0 | E16: ='Materie Prime-Conumo '!K3 -> 0 | F16: ='Materie Prime-Conumo '!L3 -> 0 | G16: ='Materie Prime-Conumo '!M3 -> 0 | H16: ='Materie Prime-Conumo '!N3 -> 2179.45 | I16: ='Materie Prime-Conumo '!O3 -> 0 | J16: ='Materie Prime-Conumo '!P3 -> 0 | K16: ='Materie Prime-Conumo '!Q3 -> 0 | ... S16: ='Materie Prime-Conumo '!Y3 -> 0
A17: Tasse e Imposte | D17: ='Tasse e Imposte'!J3 -> 0 | E17: ='Tasse e Imposte'!K3 -> 0 | F17: ='Tasse e Imposte'!L3 -> 0 | G17: ='Tasse e Imposte'!M3 -> 0 | H17: ='Tasse e Imposte'!N3 -> 800 | I17: ='Tasse e Imposte'!O3 -> 800 | J17: ='Tasse e Imposte'!P3 -> 800 | K17: ='Tasse e Imposte'!Q3 -> 800 | ... S17: ='Tasse e Imposte'!Y3 -> 0
A18: Mutui e Finaziamenti | D18: ='Mutui e Finaziamenti'!J3 -> 0 | E18: ='Mutui e Finaziamenti'!K3 -> 0 | F18: ='Mutui e Finaziamenti'!L3 -> 0 | G18: ='Mutui e Finaziamenti'!M3 -> 0 | H18: ='Mutui e Finaziamenti'!N3 -> 13888.48 | I18: ='Mutui e Finaziamenti'!O3 -> 13888.48 | J18: ='Mutui e Finaziamenti'!P3 -> 13888.48 | K18: ='Mutui e Finaziamenti'!Q3 -> 13888.48 | ... S18: ='Mutui e Finaziamenti'!Y3 -> 0
A19: Consulenze | D19: =Consulenze!J3 -> 0 | E19: =Consulenze!K3 -> 0 | F19: =Consulenze!L3 -> 0 | G19: =Consulenze!M3 -> 0 | H19: =Consulenze!N3 -> 6614.53 | I19: =Consulenze!O3 -> 354.65 | J19: =Consulenze!P3 -> 700 | K19: =Consulenze!Q3 -> 2000 | ... S19: =Consulenze!Y3 -> 0
A20: Godimento Benidi Terzi | D20: ='Godimento Beni di Terzi'!J3 -> 0 | E20: ='Godimento Beni di Terzi'!K3 -> 0 | F20: ='Godimento Beni di Terzi'!L3 -> 0 | G20: ='Godimento Beni di Terzi'!M3 -> 0 | H20: ='Godimento Beni di Terzi'!N3 -> 0 | I20: ='Godimento Beni di Terzi'!O3 -> 0 | J20: ='Godimento Beni di Terzi'!P3 -> 0 | K20: ='Godimento Beni di Terzi'!Q3 -> 0 | ... S20: ='Godimento Beni di Terzi'!Y3 -> 0
A21: Varie ed Eventuali | D21: =' Varie ed Eventuali'!J3 -> 0 | E21: =' Varie ed Eventuali'!K3 -> 0 | F21: =' Varie ed Eventuali'!L3 -> 0 | G21: =' Varie ed Eventuali'!M3 -> 0 | H21: =' Varie ed Eventuali'!N3 -> 177405.25 | I21: =' Varie ed Eventuali'!O3 -> 15000 | J21: =' Varie ed Eventuali'!P3 -> 15000 | K21: =' Varie ed Eventuali'!Q3 -> 15000 | ... S21: =' Varie ed Eventuali'!Y3 -> 0
A22: Canoni e servizi | D22: ='Canoni e servizi'!J3 -> 0 | E22: ='Canoni e servizi'!K3 -> 0 | F22: ='Canoni e servizi'!L3 -> 0 | G22: ='Canoni e servizi'!M3 -> 0 | H22: ='Canoni e servizi'!N3 -> 475.8 | I22: ='Canoni e servizi'!O3 -> 600 | J22: ='Canoni e servizi'!P3 -> 0 | K22: ='Canoni e servizi'!Q3 -> 0 | ... S22: ='Canoni e servizi'!Y3 -> 0
A23: Caparre da girocantare aOrti | C23: =Nota!B4 -> 130556.57 | D23: 0 | E23: 0 | F23: 0 | G23: 0 | H23: 0 | I23: 0 | J23: 0 | K23: 0 | L23: 0 | M23: 0
A27: TOTALE USCITE | D27: =SUM(D14:D26) -> 0 | E27: =SUM(E14:E26) -> 0 | F27: =SUM(F14:F26) -> 0 | G27: =SUM(G14:G26) -> 0 | H27: =SUM(H14:H26) -> 236488.67 | I27: =SUM(I14:I26) -> 52981.29 | J27: =SUM(J14:J26) -> 46238.48 | K27: =SUM(K14:K26) -> 46938.48 | ... S27: =SUM(S14:S26) -> 0
A29: CASH FLOW | C29: =C12-C27 -> 0 | D29: =D12-D27 -> 0 | E29: =E12-E27 -> 0 | F29: =F12-F27 -> 0 | G29: =G12-G27 -> 0 | H29: =H12-H27 -> 330261.33 | I29: =I12-I27 -> 207768.71 | J29: =J12-J27 -> -7488.48 | ... S29: =S12-S27 -> 0
A31: Saldo Banca Sella | C31: 8970.54
A32: Saldo MPS | C32: 178357.54
A33: Saldo Intesa | C33: 2498.64
A35: TOTALE BANCHE | C35: =SUM(C31:C34) -> 189826.72 | D35: =SUM(D31:D34) -> 0 | E35: =SUM(E31:E34) -> 0 | F35: =SUM(F31:F34) -> 0 | G35: =SUM(G31:G34) -> 0 | H35: =SUM(H31:H34) -> 0 | I35: =SUM(I31:I34) -> 0 | J35: =SUM(J31:J34) -> 0 | ... S35: =SUM(S31:S34) -> 0
A38: Saldo di Periodo/Proiettato | C38: =C35 -> 189826.72 | D38: =D3+(D29+D35) -> 189826.72 | E38: =E3+(E29+E35) -> 189826.72 | F38: =F3+(F29+F35) -> 189826.72 | G38: =G3+(G29+G35) -> 189826.72 | H38: =H3+(H29+H35) -> 520088.05 | I38: =I3+(I29+I35) -> 727856.76 | J38: =J3+(J29+J35) -> 720368.28 | K38: =K3+(K29+K35) -> 677179.8 | ... S38: =S3+(S29+S35) -> 573102.84
A40: Affidamento Sella | C40: 150000 | D40: 150000 | E40: 150000 | F40: 150000 | G40: 150000 | H40: 150000 | I40: 150000 | J40: 150000 | K40: 150000 | L40: 150000 | M40: 150000
A44: TOTALE AFFIDAMENTI | C44: =SUM(C40:C43) -> 150000 | D44: =SUM(D40:D43) -> 150000 | E44: =SUM(E40:E43) -> 150000 | F44: =SUM(F40:F43) -> 150000 | G44: =SUM(G40:G43) -> 150000 | H44: =SUM(H40:H43) -> 150000 | I44: =SUM(I40:I43) -> 150000 | J44: =SUM(J40:J43) -> 150000 | ... S44: =SUM(S40:S43) -> 0
A46: CASH FLOW CON AFFID. | C46: =C38+C44 -> 339826.72 | D46: =D38+D44 -> 339826.72 | E46: =E38+E44 -> 339826.72 | F46: =F38+F44 -> 339826.72 | G46: =G38+G44 -> 339826.72 | H46: =H38+H44 -> 670088.05 | I46: =I38+I44 -> 877856.76 | J46: =J38+J44 -> 870368.28 | ... S46: =S38+S44 -> 573102.84

Sheet Salari e Stipendi
D1: 2025 | H1: 2026 | T1: 2027
D2: SETTEMBRE | E2: OTTOBRE | F2: NOVEMBRE | G2: DICEMBRE | H2: GENNAIO | I2: FEBBRAIO | J2: MARZO | K2: APRILE | L2: MAGGIO | M2: GIUGNO | N2: LUGLIO | O2: AGOSTO | P2: SETTEMBRE | Q2: OTTOBRE | R2: NOVEMBRE | S2: DICEMBRE | T2: GENNAIO | U2: FEBBRAIO | V2: MARZO | W2: APRILE | X2: MAGGIO | Y2: GIUGNO
B3: Salari e Stipendi | C3: =SUM(D3:Y3) -> 89000 | D3: =SUM(D4:D134) -> 0 | E3: =SUM(E4:E134) -> 0 | F3: =SUM(F4:F134) -> 0 | G3: =SUM(G4:G134) -> 0 | H3: =SUM(H4:H134) -> 0 | I3: =SUM(I4:I134) -> 0 | J3: =SUM(J4:J134) -> 0 | K3: =SUM(K4:K134) -> 0 | ... Y3: =SUM(Y4:Y134) -> 0
B4: Salari | C4: =SUM(D4:Y4) -> 56000 | F4: 0 | G4: 0 | N4: =10000+1000 -> 11000 | O4: 11000 | P4: 10000 | Q4: 9000 | R4: 10000 | S4: 5000
B5: F24 | F5: 0 | G5: 0 | N5: 5000 | O5: 10000 | P5: 5000 | Q5: 5000 | R5: 5000 | S5: 3000

Sheet Utenze
D1: 2025 | H1: 2026 | T1: 2027
D2: SETTEMBRE | E2: OTTOBRE | F2: NOVEMBRE | G2: DICEMBRE | H2: GENNAIO | I2: FEBBRAIO | J2: MARZO | K2: APRILE | L2: MAGGIO | M2: GIUGNO | N2: LUGLIO | O2: AGOSTO | P2: SETTEMBRE | Q2: OTTOBRE | R2: NOVEMBRE | S2: DICEMBRE | T2: GENNAIO | U2: FEBBRAIO | V2: MARZO | W2: APRILE | X2: MAGGIO | Y2: GIUGNO
B3: Utenze | C3: =SUM(D3:Y3) -> 23963.32 | D3: =SUM(D4:D133) -> 0 | E3: =SUM(E4:E133) -> 0 | F3: =SUM(F4:F133) -> 0 | G3: =SUM(G4:G133) -> 0 | H3: =SUM(H4:H133) -> 0 | I3: =SUM(I4:I133) -> 0 | J3: =SUM(J4:J133) -> 0 | K3: =SUM(K4:K133) -> 0 | ... Y3: =SUM(Y4:Y133) -> 0
A4: RID | B4: Energia elettrica | C4: =SUM(D4:Y4) -> 3980 | F4: 0 | G4: 0 | N4: =130 -> 130 | O4: 800 | P4: 850 | Q4: 800 | R4: 900 | S4: 500
A5: RID | B5: Gas | C5: =SUM(D5:Y5) -> 0 | F5: 0
B6: Ausino - rateizzo | C6: =SUM(D6:Y6) -> 18147.18 | F6: 0 | N6: 17348.16 | O6: 349.02 | Q6: 450
A7: RID | B7: Vodafone (da ribaltare) | C7: =SUM(D7:Y7) -> 109.8 | N7: 109.8
A8: 1592 | B8: FASTWEB SPA | C8: =SUM(D8:Y8) -> 1537.2 | N8: 1537.2
A9: 30 | B9: 4G ENERGIA SRL | C9: =SUM(D9:Y9) -> 189.14 | O9: 189.14
C10: =SUM(D10:Y10) -> 0
C11: =SUM(D11:Y11) -> 0
C12: =SUM(D12:Y12) -> 0
C13: =SUM(D13:Y13) -> 0
C14: =SUM(D14:Y14) -> 0
C15: =SUM(D15:Y15) -> 0
C16: =SUM(D16:Y16) -> 0
C17: =SUM(D17:Y17) -> 0
C18: =SUM(D18:Y18) -> 0
C19: =SUM(D19:Y19) -> 0
C20: =SUM(D20:Y20) -> 0
C21: =SUM(D21:Y21) -> 0
... C61: =SUM(D61:Y61) -> 0

Sheet Materie Prime-Conumo 
D1: 2025 | H1: 2026 | T1: 2027
D2: SETTEMBRE | E2: OTTOBRE | F2: NOVEMBRE | G2: DICEMBRE | H2: GENNAIO | I2: FEBBRAIO | J2: MARZO | K2: APRILE | L2: MAGGIO | M2: GIUGNO | N2: LUGLIO | O2: AGOSTO | P2: SETTEMBRE | Q2: OTTOBRE | R2: NOVEMBRE | S2: DICEMBRE | T2: GENNAIO | U2: FEBBRAIO | V2: MARZO | W2: APRILE | X2: MAGGIO | Y2: GIUGNO
B3: Materie Prime e Consumo | C3: =SUM(D3:Y3) -> 2179.45 | D3: =SUM(D4:D164) -> 0 | E3: =SUM(E4:E164) -> 0 | F3: =SUM(F4:F164) -> 0 | G3: =SUM(G4:G164) -> 0 | H3: =SUM(H4:H164) -> 0 | I3: =SUM(I4:I164) -> 0 | J3: =SUM(J4:J164) -> 0 | K3: =SUM(K4:K164) -> 0 | ... Y3: =SUM(Y4:Y164) -> 0
A4: 48 | B4: B&G Di Palo | C4: =SUM(D4:Y4) -> 75.25 | D4: 0 | F4: 0 | G4: 0 | N4: 75.25
A5: 596 | B5: BABBI SRL | C5: =SUM(D5:Y5) -> 175.2 | N5: 175.2
B6: J.F. Amonn | C6: =SUM(D6:Y6) -> 463.6 | N6: 463.6
C7: =SUM(D7:Y7) -> 0
C8: =SUM(D8:Y8) -> 0
C9: =SUM(D9:Y9) -> 0
C10: =SUM(D10:Y10) -> 0
A11: 1273.38 | B11: CoIrEs SRL | C11: =SUM(D11:Y11) -> 1273.38 | N11: 1273.38
B12: Creative Idea Snc | C12: =SUM(D12:Y12) -> 0
B13: De Riso | C13: =SUM(D13:Y13) -> 27 | N13: 27
B14: EURO GROUP NETWORK S.R.L. | C14: =SUM(D14:Y14) -> 0
B15: Foraggio Srl | C15: =SUM(D15:Y15) -> 0
B16: IDRO-TOP SRL | C16: =SUM(D16:Y16) -> 64.68 | N16: 64.68
B17: INDEL B | C17: =SUM(D17:Y17) -> 0
B18: Locali d'autore | C18: =SUM(D18:Y18) -> 0
B19: Mediterraneo | C19: =SUM(D19:Y19) -> 0 | F19: 0 | G19: 0
B20: Ninni | C20: =SUM(D20:Y20) -> 0 | F20: 0 | G20: 0
B21: Oceano Distribuzione | C21: =SUM(D21:Y21) -> 0
B22: Pasticceria Trieste | C22: =SUM(D22:Y22) -> 0
B23: Rastrelli Antonia | C23: =SUM(D23:Y23) -> 55.33 | N23: 55.33
A24: 412036.53 | B24: Panorama Company Srl | C24: =SUM(D24:Y24) -> 0
B25: Paravia | C25: =SUM(D25:Y25) -> 0
B26: Primavera Servizi Srl | C26: =SUM(D26:Y26) -> 0
B27: Giardiniello | C27: =SUM(D27:Y27) -> 0
A28: 45440 | B28: Tecno Campania | C28: =SUM(D28:Y28) -> 0
B29: Vulaj (Ceramica) | C29: =SUM(D29:Y29) -> 45.01 | F29: 0 | G29: 0 | N29: 45.01

Sheet Tasse e Imposte
D1: 2025 | H1: 2026 | T1: 2027
D2: SETTEMBRE | E2: OTTOBRE | F2: NOVEMBRE | G2: DICEMBRE | H2: GENNAIO | I2: FEBBRAIO | J2: MARZO | K2: APRILE | L2: MAGGIO | M2: GIUGNO | N2: LUGLIO | O2: AGOSTO | P2: SETTEMBRE | Q2: OTTOBRE | R2: NOVEMBRE | S2: DICEMBRE | T2: GENNAIO | U2: FEBBRAIO | V2: MARZO | W2: APRILE | X2: MAGGIO | Y2: GIUGNO
B3: Tasse e Imposte | C3: =SUM(D3:Y3) -> 32000 | D3: =SUM(D4:D131) -> 0 | E3: =SUM(E4:E131) -> 0 | F3: =SUM(F4:F131) -> 0 | G3: =SUM(G4:G131) -> 0 | H3: =SUM(H4:H131) -> 0 | I3: =SUM(I4:I131) -> 0 | J3: =SUM(J4:J131) -> 0 | K3: =SUM(K4:K131) -> 0 | ... Y3: =SUM(Y4:Y131) -> 0
B4: IMU | C4: =SUM(D4:Y4) -> 0 | G4: 0
B5: I ACCONTO IMPOSTE | C5: =SUM(D5:Y5) -> 0 | F5: 0
B6: TARI | C6: =SUM(F6:S6) -> 0
B7: IVA | C7: =SUM(E7:S7) -> 4000 | F7: 0 | G7: 0 | N7: 800 | O7: 800 | P7: 800 | Q7: 800 | R7: 800
B8: IRES | C8: =SUM(E8:S8) -> 28000 | F8: 0 | R8: 28000
B9: IRAP | C9: =SUM(E9:S9) -> 0 | F9: 0
B10: AFFRANCAMENTO | C10: =SUM(E10:S10) -> 0
A11: 68696 | B11: ARRETRATO IMPOSTE | C11: =SUM(E11:S11) -> 0
B12: ARRETRATO IMU | C12: =SUM(D12:Y12) -> 0 | F12: 0 | G12: 0
B13: Ritenute professionisti (1040) | C13: =SUM(D13:Y13) -> 0
C14: =SUM(D14:Y14) -> 0
C15: =SUM(D15:Y15) -> 0
C16: =SUM(D16:Y16) -> 0
C17: =SUM(D17:Y17) -> 0
C18: =SUM(D18:Y18) -> 0
C19: =SUM(D19:Y19) -> 0
C20: =SUM(D20:Y20) -> 0
C21: =SUM(D21:Y21) -> 0
C22: =SUM(D22:Y22) -> 0
C23: =SUM(D23:Y23) -> 0
C24: =SUM(D24:Y24) -> 0
C25: =SUM(D25:Y25) -> 0
... C59: =SUM(D59:Y59) -> 0

Sheet Mutui e Finaziamenti
D1: 2025 | H1: 2026 | T1: 2027
D2: SETTEMBRE | E2: OTTOBRE | F2: NOVEMBRE | G2: DICEMBRE | H2: GENNAIO | I2: FEBBRAIO | J2: MARZO | K2: APRILE | L2: MAGGIO | M2: GIUGNO | N2: LUGLIO | O2: AGOSTO | P2: SETTEMBRE | Q2: OTTOBRE | R2: NOVEMBRE | S2: DICEMBRE | T2: GENNAIO | U2: FEBBRAIO | V2: MARZO | W2: APRILE | X2: MAGGIO | Y2: GIUGNO
B3: Mutui e Finanaziamenti | C3: =SUM(D3:Y3) -> 83330.88 | D3: =SUM(D4:D134) -> 0 | E3: =SUM(E4:E134) -> 0 | F3: =SUM(F4:F134) -> 0 | G3: =SUM(G4:G134) -> 0 | H3: =SUM(H4:H134) -> 0 | I3: =SUM(I4:I134) -> 0 | J3: =SUM(J4:J134) -> 0 | K3: =SUM(K4:K134) -> 0 | ... Y3: =SUM(Y4:Y134) -> 0
B4: Mutuo Banca Intesa | C4: =SUM(D4:Y4) -> 54000 | F4: 0 | N4: 9000 | O4: 9000 | P4: 9000 | Q4: 9000 | R4: 9000 | S4: 9000
B5: Finanziamento Sella | C5: =SUM(D5:Y5) -> 0 | F5: 0
B6: Finanziamento MPS 75K | C6: =SUM(D6:Y6) -> 8330.88 | F6: 0 | N6: 1388.48 | O6: 1388.48 | P6: 1388.48 | Q6: 1388.48 | R6: 1388.48 | S6: 1388.48
B7: Finanziamento MPS 1200K | C7: =SUM(D7:Y7) -> 21000 | N7: 3500 | O7: 3500 | P7: 3500 | Q7: 3500 | R7: 3500 | S7: 3500
C8: =SUM(D8:Y8) -> 0
C9: =SUM(D9:Y9) -> 0
C10: =SUM(D10:Y10) -> 0
C11: =SUM(D11:Y11) -> 0
C12: =SUM(D12:Y12) -> 0
C13: =SUM(D13:Y13) -> 0
C14: =SUM(D14:Y14) -> 0
C15: =SUM(D15:Y15) -> 0
C16: =SUM(D16:Y16) -> 0
C17: =SUM(D17:Y17) -> 0
C18: =SUM(D18:Y18) -> 0
C19: =SUM(D19:Y19) -> 0
... C62: =SUM(D62:Y62) -> 0

Sheet Consulenze
D1: 2025 | H1: 2026 | T1: 2027
D2: SETTEMBRE | E2: OTTOBRE | F2: NOVEMBRE | G2: DICEMBRE | H2: GENNAIO | I2: FEBBRAIO | J2: MARZO | K2: APRILE | L2: MAGGIO | M2: GIUGNO | N2: LUGLIO | O2: AGOSTO | P2: SETTEMBRE | Q2: OTTOBRE | R2: NOVEMBRE | S2: DICEMBRE | T2: GENNAIO | U2: FEBBRAIO | V2: MARZO | W2: APRILE | X2: MAGGIO | Y2: GIUGNO
B3: Consulenze | C3: =SUM(D3:Y3) -> 10269.18 | D3: =SUM(D4:D134) -> 0 | E3: =SUM(E4:E134) -> 0 | F3: =SUM(F4:F134) -> 0 | G3: =SUM(G4:G134) -> 0 | H3: =SUM(H4:H134) -> 0 | I3: =SUM(I4:I134) -> 0 | J3: =SUM(J4:J134) -> 0 | K3: =SUM(K4:K134) -> 0 | ... Y3: =SUM(Y4:Y134) -> 0
B4: Consulenza del lavoro | C4: =SUM(D4:Y4) -> 1900 | F4: 0 | G4: 0 | N4: 600 | P4: 700 | S4: 600
B5: Consulenza fiscale | C5: =SUM(D5:Y5) -> 4000 | N5: 2000 | Q5: 2000
B6: Consulenza legale | C6: =SUM(D6:Y6) -> 0
B7: Prev. Consulenze Legali | C7: =SUM(D7:Y7) -> 0
B8: ALDEN | C8: =SUM(D8:Y8) -> 244 | N8: 244
B9: Revisore - Punzi | C9: =SUM(D9:Y9) -> 0
B10: Cons. Marketing - Travaglini Armando | C10: =SUM(D10:Y10) -> 0
B11: DG NETWORK | C11: =SUM(D11:Y11) -> 0
B12: Geologo Antonio Apicella | C12: =SUM(D12:Y12) -> 1015.04 | N12: 1015.04
A13: 1027 | B13: CAFARELLI MASSIMILIANO | C13: =SUM(D13:Y13) -> 30 | N13: 30
B14: CSW Engineering s.r.l | C14: =SUM(D14:Y14) -> 226.92 | N14: 226.92
A15: 41 | B15: Giordano Associati S.r.l Socio Unico | C15: =SUM(D15:Y15) -> 2853.22 | N15: 2498.57 | O15: 354.65
C16: =SUM(D16:Y16) -> 0
C17: =SUM(D17:Y17) -> 0
C18: =SUM(D18:Y18) -> 0
C19: =SUM(D19:Y19) -> 0
C20: =SUM(D20:Y20) -> 0
C21: =SUM(D21:Y21) -> 0
C22: =SUM(D22:Y22) -> 0
C23: =SUM(D23:Y23) -> 0
C24: =SUM(D24:Y24) -> 0
C25: =SUM(D25:Y25) -> 0
C26: =SUM(D26:Y26) -> 0
C27: =SUM(D27:Y27) -> 0
... C62: =SUM(D62:Y62) -> 0

Sheet Godimento Beni di Terzi
D1: 2025 | H1: 2026 | T1: 2027
D2: SETTEMBRE | E2: OTTOBRE | F2: NOVEMBRE | G2: DICEMBRE | H2: GENNAIO | I2: FEBBRAIO | J2: MARZO | K2: APRILE | L2: MAGGIO | M2: GIUGNO | N2: LUGLIO | O2: AGOSTO | P2: SETTEMBRE | Q2: OTTOBRE | R2: NOVEMBRE | S2: DICEMBRE | T2: GENNAIO | U2: FEBBRAIO | V2: MARZO | W2: APRILE | X2: MAGGIO | Y2: GIUGNO
A3: =SUM(A4:A31) -> 33600 | B3: Godimento Beni di Terzi | C3: =SUM(D3:Y3) -> 0 | D3: =SUM(D4:D134) -> 0 | E3: =SUM(E4:E134) -> 0 | F3: =SUM(F4:F134) -> 0 | G3: =SUM(G4:G134) -> 0 | H3: =SUM(H4:H134) -> 0 | I3: =SUM(I4:I134) -> 0 | J3: =SUM(J4:J134) -> 0 | K3: =SUM(K4:K134) -> 0 | ... Y3: =SUM(Y4:Y134) -> 0
A4: 14400 | B4: 2024 - Arretrati Residence 3x€4.800 | C4: =SUM(D4:Y4) -> 0
A5: 19200 | B5: 2025 - Arretrati Residence 4x€4.800 | C5: =SUM(D5:Y5) -> 0
C6: =SUM(D6:Y6) -> 0
C7: =SUM(D7:Y7) -> 0
C8: =SUM(D8:Y8) -> 0
C9: =SUM(D9:Y9) -> 0
C10: =SUM(D10:Y10) -> 0
C11: =SUM(D11:Y11) -> 0
C12: =SUM(D12:Y12) -> 0
C13: =SUM(D13:Y13) -> 0
C14: =SUM(D14:Y14) -> 0
C15: =SUM(D15:Y15) -> 0
C16: =SUM(D16:Y16) -> 0
C17: =SUM(D17:Y17) -> 0
... C62: =SUM(D62:Y62) -> 0

Sheet Canoni e servizi
D1: 2025 | H1: 2026 | T1: 2027
D2: SETTEMBRE | E2: OTTOBRE | F2: NOVEMBRE | G2: DICEMBRE | H2: GENNAIO | I2: FEBBRAIO | J2: MARZO | K2: APRILE | L2: MAGGIO | M2: GIUGNO | N2: LUGLIO | O2: AGOSTO | P2: SETTEMBRE | Q2: OTTOBRE | R2: NOVEMBRE | S2: DICEMBRE | T2: GENNAIO | U2: FEBBRAIO | V2: MARZO | W2: APRILE | X2: MAGGIO | Y2: GIUGNO
B3: Canoni e servizi | C3: =SUM(D3:Y3) -> 1075.8 | D3: =SUM(D4:D132) -> 0 | E3: =SUM(E4:E132) -> 0 | F3: =SUM(F4:F132) -> 0 | G3: =SUM(G4:G132) -> 0 | H3: =SUM(H4:H132) -> 0 | I3: =SUM(I4:I132) -> 0 | J3: =SUM(J4:J132) -> 0 | K3: =SUM(K4:K132) -> 0 | ... Y3: =SUM(Y4:Y132) -> 0
B4: Pin App | C4: =SUM(D4:Y4) -> 0 | F4: 0 | H4: 0
B5: Spiagge | C5: =SUM(D5:Y5) -> 600 | O5: 600
B6: Spese Bancarie | C6: =SUM(D6:Y6) -> 0
B7: Banca sella - canone e-commerce RID | C7: =SUM(D7:Y7) -> 0
A8: 1558 | B8: Oliva Coperture | C8: =SUM(D8:Y8) -> 0
A9: 15 | B9: Altamira Srl | C9: =SUM(D9:Y9) -> 0
A10: 52 | B10: Aruba S.p.A. | C10: =SUM(D10:Y10) -> 0
A11: 16 | B11: SOFTWARE STUDIO S.R.L. | C11: =SUM(D11:Y11) -> 475.8 | N11: 475.8
B12: Amalfi Web | C12: =SUM(D12:Y12) -> 0
B13: Commissioni Pos | C13: =SUM(D13:Y13) -> 0
A14: RID | C14: =SUM(D14:Y14) -> 0
A15: 1069 | B15: TOPWHITE DI DANIELE RAVELLI | C15: =SUM(D15:Y15) -> 0
C16: =SUM(D16:Y16) -> 0
C17: =SUM(D17:Y17) -> 0
C18: =SUM(D18:Y18) -> 0
C19: =SUM(D19:Y19) -> 0
C20: =SUM(D20:Y20) -> 0
C21: =SUM(D21:Y21) -> 0
C22: =SUM(D22:Y22) -> 0
C23: =SUM(D23:Y23) -> 0
C24: =SUM(D24:Y24) -> 0
C25: =SUM(D25:Y25) -> 0
C26: =SUM(D26:Y26) -> 0
C27: =SUM(D27:Y27) -> 0
... C61: =SUM(D61:Y61) -> 0

Sheet  Varie ed Eventuali
D1: 2025 | H1: 2026 | T1: 2027
D2: SETTEMBRE | E2: OTTOBRE | F2: NOVEMBRE | G2: DICEMBRE | H2: GENNAIO | I2: FEBBRAIO | J2: MARZO | K2: APRILE | L2: MAGGIO | M2: GIUGNO | N2: LUGLIO | O2: AGOSTO | P2: SETTEMBRE | Q2: OTTOBRE | R2: NOVEMBRE | S2: DICEMBRE | T2: GENNAIO | U2: FEBBRAIO | V2: MARZO | W2: APRILE | X2: MAGGIO | Y2: GIUGNO
C3: =SUM(D3:Y3) -> 252405.25 | D3: =SUM(D5:D135) -> 0 | E3: =SUM(E5:E135) -> 0 | F3: =SUM(F5:F135) -> 0 | G3: =SUM(G5:G135) -> 0 | H3: =SUM(H5:H135) -> 0 | I3: =SUM(I5:I135) -> 0 | J3: =SUM(J5:J135) -> 0 | K3: =SUM(K5:K135) -> 0 | L3: =+L4+L5+L6+L7+L8+L9+L10+L12+L13+L14+L15+L16+L17+L18 -> 0 | M3: =+M4+M5+M6+M7+M8+M9+M10+M12+M13+M14+M15+M16+M17+M18 -> 0 | N3: =+N4+N5+N6+N7+N8+N9+N10+N12+N13+N14+N15+N16+N17+N18 -> 177405.25 | O3: =+O4+O5+O6+O7+O8+O9+O10+O12+O13+O14+O15+O16+O17+O18 -> 15000 | P3: =+P4+P5+P6+P7+P8+P9+P10+P12+P13+P14+P15+P16+P17+P18 -> 15000 | Q3: =+Q4+Q5+Q6+Q7+Q8+Q9+Q10+Q12+Q13+Q14+Q15+Q16+Q17+Q18 -> 15000 | R3: =+R4+R5+R6+R7+R8+R9+R10+R12+R13+R14+R15+R16+R17+R18 -> 15000 | S3: =+S4+S5+S6+S7+S8+S9+S10+S12+S13+S14+S15+S16+S17+S18 -> 15000 | ... Y3: =+Y4+Y5+Y6+Y7+Y8+Y9+Y10+Y12+Y13+Y14+Y15+Y16+Y17+Y18 -> 0
B4: Variee ed Eventuali | N4: 15000 | O4: 15000 | P4: 15000 | Q4: 15000 | R4: 15000 | S4: 15000
A5: 266 | B5: B & T SpA | C5: =SUM(D5:Y5) -> 0 | F5: 0
A6: 1734 | B6: Ce.Di.S. srl | C6: =SUM(D6:Y6) -> 0
A7: 716 | B7: CERAMICA D'ARTE SICIGNANO SRL | C7: =SUM(D7:Y7) -> 61500.57 | N7: 61500.57
A8: 1640 | B8: Domus Tappezzeria D'Arredo S.R.L. | C8: =SUM(D8:Y8) -> 0
A9: 1607 | B9: LAUDATO GRU DI LAUDATO FRANCESCO | C9: =SUM(D9:Y9) -> 1220 | N9: 1220
A10: 734 | B10: LEONE S.R.L. | C10: =SUM(D10:Y10) -> 1518 | N10: 1518
A11: 1008 | B11: MIELE GIUSEPPE E FIGLI SPA | C11: =SUM(D11:Y11) -> 0
A12: 1672 | B12: OMBRELLONI LETTINI ITALIA S.R.L. | C12: =SUM(D12:Y12) -> 8771.8 | N12: 8771.8
A13: 64 | B13: PARAVIA ELEVATORS SRL | C13: =SUM(D13:Y13) -> 0
A14: 863 | B14: SALA GIANPIERO | C14: =SUM(D14:Y14) -> 88139.3 | N14: 88139.3
A15: 121 | B15: Santelia Luigi | C15: =SUM(D15:Y15) -> 0
A16: 1214 | B16: VDA GROUP S.p.A. a socio unico | C16: =SUM(D16:Y16) -> 1084.58 | N16: 1084.58
A17: 1662 | B17: Indel B Spa | C17: =SUM(D17:Y17) -> 0
A18: 1054 | B18: O.V.I.T. SRL | N18: 171
A19: 1034 | B19: ORIL SRL | N19: 66.08

Sheet Nota
A1: Debiti non inseriti nel piano
A3: Fornitore | B3: Importo
A4: Caparre da girocantare aOrti | B4: 130556.57
A5: SDP | B5: 33600
A7: Panorama Company | B7: 412036.53

Sheet DA MAPPARE
A1: Fornitori NON mappati in d_fornitori.csv — assegnare una voce (hotelops fornitori) e rigenerare
A2: Cod | B2: Nome (da export) | C2: GENNAIO | D2: FEBBRAIO | E2: MARZO | F2: APRILE | G2: MAGGIO | H2: GIUGNO | I2: LUGLIO | J2: AGOSTO | K2: SETTEMBRE | L2: OTTOBRE | M2: NOVEMBRE | N2: DICEMBRE

Sheet ESCLUSI
A1: Fornitori ESCLUSI dalla cassa per scelta (is_excluded) — fuori dal saldo proiettato. NON sono un TODO: il motivo è in colonna Motivo.
A2: Cod | B2: Nome (da CSV) | C2: GENNAIO | D2: FEBBRAIO | E2: MARZO | F2: APRILE | G2: MAGGIO | H2: GIUGNO | I2: LUGLIO | J2: AGOSTO | K2: SETTEMBRE | L2: OTTOBRE | M2: NOVEMBRE | N2: DICEMBRE | O2: Motivo
A3: 1033 | B3: EURO GROUP NETWORK S.R.L. | G3: 31.99 | O3: una_tantum
A4: 1048 | B4: MEDITERRANEO SNC DI TRAMONTANO | G4: 59.99 | O4: una_tantum
A5: 264 | B5: PANORAMA COMPANY S.R.L. | G5: 412036.53 | O5: intercompany
A6: 796 | B6: RAIA LIBERATO | G6: 66.01 | O6: una_tantum
A7: 236 | B7: RISTORANTE GIARDINIELLO SRL | G7: 97.5 | O7: una_tantum
A8: 85 | B8: TECNO CAMPANIA SRL | G8: 63440 | O8: una_tantum

Sheet DA MAPPARE1
A1: Fornitori NON mappati in d_fornitori.csv — assegnare una voce (hotelops fornitori) e rigenerare
A2: Cod | B2: Nome (da export) | C2: GENNAIO | D2: FEBBRAIO | E2: MARZO | F2: APRILE | G2: MAGGIO | H2: GIUGNO | I2: LUGLIO | J2: AGOSTO | K2: SETTEMBRE | L2: OTTOBRE | M2: NOVEMBRE | N2: DICEMBRE

Sheet ESCLUSI1
A1: Fornitori ESCLUSI dalla cassa per scelta (is_excluded) — fuori dal saldo proiettato. NON sono un TODO: il motivo è in colonna Motivo.
A2: Cod | B2: Nome (da CSV) | C2: GENNAIO | D2: FEBBRAIO | E2: MARZO | F2: APRILE | G2: MAGGIO | H2: GIUGNO | I2: LUGLIO | J2: AGOSTO | K2: SETTEMBRE | L2: OTTOBRE | M2: NOVEMBRE | N2: DICEMBRE | O2: Motivo
A3: 1033 | B3: EURO GROUP NETWORK S.R.L. | H3: 31.99 | O3: una_tantum
A4: 1048 | B4: MEDITERRANEO SNC DI TRAMONTANO | H4: 59.99 | O4: una_tantum
A5: 264 | B5: PANORAMA COMPANY S.R.L. | H5: 412036.53 | O5: intercompany
A6: 796 | B6: RAIA LIBERATO | H6: 66.01 | O6: una_tantum
A7: 236 | B7: RISTORANTE GIARDINIELLO SRL | H7: 97.5 | O7: una_tantum
A8: 85 | B8: TECNO CAMPANIA SRL | H8: 63440 | O8: una_tantum

Sheet DA MAPPARE2
A1: Fornitori NON mappati in d_fornitori.csv — assegnare una voce (hotelops fornitori) e rigenerare
A2: Cod | B2: Nome (da export) | C2: GENNAIO | D2: FEBBRAIO | E2: MARZO | F2: APRILE | G2: MAGGIO | H2: GIUGNO | I2: LUGLIO | J2: AGOSTO | K2: SETTEMBRE | L2: OTTOBRE | M2: NOVEMBRE | N2: DICEMBRE
A3: 671 | B3: 2A SYSTEMS SRL | I3: 220
A4: 722 | B4: Barbella Srl | I4: 939.4
A5: 1819 | B5: FUEL STATION SRL | I5: 120
A6: 1795 | B6: HYGIEN TECH S.R.L. | I6: 1365.83
A7: 1078 | B7: Intesa Sanpaolo S.p.a | I7: 67.1
A8: 414 | B8: NEXI PAYMENTS S.p.A. | I8: 25.44

Sheet ESCLUSI2
A1: Fornitori ESCLUSI dalla cassa per scelta (is_excluded) — fuori dal saldo proiettato. NON sono un TODO: il motivo è in colonna Motivo.
A2: Cod | B2: Nome (da CSV) | C2: GENNAIO | D2: FEBBRAIO | E2: MARZO | F2: APRILE | G2: MAGGIO | H2: GIUGNO | I2: LUGLIO | J2: AGOSTO | K2: SETTEMBRE | L2: OTTOBRE | M2: NOVEMBRE | N2: DICEMBRE | O2: Motivo
A3: 1033 | B3: EURO GROUP NETWORK S.R.L. | I3: 31.99 | O3: una_tantum
A4: 1048 | B4: MEDITERRANEO SNC DI TRAMONTANO | I4: 59.99 | O4: una_tantum
A5: 264 | B5: PANORAMA COMPANY S.R.L. | I5: 412036.53 | O5: intercompany
A6: 796 | B6: RAIA LIBERATO | I6: 66.01 | O6: una_tantum
A7: 236 | B7: RISTORANTE GIARDINIELLO SRL | I7: 97.5 | O7: una_tantum
A8: 85 | B8: TECNO CAMPANIA SRL | I8: 45440 | O8: una_tantum
