Workbook

Sheet ✓ Controlli
A1: 🔍 AUDIT PIANO FINANZIARIO INTUR
A2: Controlli live — per il mese dopo: aggiorna saldi banche e cancella i mesi passati dai fogli dettaglio
A4: # | B4: ESITO | C4: CONTROLLO
A5: ERRORI
A6: 1 | B6: {=IF(SUMPRODUCT(ISERROR('Piano Finanziario'!C3:S46)*1)=0,"OK","ERRORE")} | C6: Zero errori nel Piano Finanziario
A7: 2 | B7: {=IF(SUMPRODUCT(ISERROR('Salari e Stipendi'!C3:Y5)*1)+SUMPRODUCT(ISERROR(Utenze!C3:Y61)*1)+SUMPRODUCT(ISERROR('Materie Prime-Conumo '!C3:Y29)*1)+SUMPRODUCT(ISERROR('Tasse e Imposte'!C3:Y59)*1)+SUMPRODUCT(ISERROR('Mutui e Finaziamenti'!C3:Y62)*1)+SUMPRODUCT(ISERROR(Consulenze!C3:Y62)*1)+SUMPRODUCT(ISERROR('Godimento Beni di Terzi'!C3:Y62)*1)+SUMPRODUCT(ISERROR(' Varie ed Eventuali'!C3:Y19)*1)+SUMPRODUCT(ISERROR('Canoni e servizi'!C3:Y61)*1)=0,"OK","ERRORE")} | C7: Zero errori in tutti i fogli dettaglio
A9: ENTRATE
A10: 3 | B10: =IF(ABS(SUM('Piano Finanziario'!D12:S12)-SUM('Piano Finanziario'!D5:S11))<0.01,"OK","ERRORE") | C10: Totale Entrate = somma righe (tutti i mesi)
A11: 4 | B11: =IF(ABS(SUM('Piano Finanziario'!D27:S27)-SUM('Piano Finanziario'!D14:S26))<0.01,"OK","ERRORE") | C11: Totale Uscite = somma dettaglio (tutti i mesi)
A12: 5 | B12: =IF(ABS(SUM('Piano Finanziario'!D29:S29)-(SUM('Piano Finanziario'!D12:S12)-SUM('Piano Finanziario'!D27:S27)))<0.01,"OK","ERRORE") | C12: Cash Flow = Entrate - Uscite (tutti i mesi)
A14: LINK FOGLI
A15: 6 | B15: {=IF(ABS(SUM('Piano Finanziario'!D14:S14)-SUMPRODUCT(('Salari e Stipendi'!D3:Y3)*(COLUMN('Salari e Stipendi'!D3:Y3)>=MATCH('Piano Finanziario'!D2,'Salari e Stipendi'!D2:Y2,0)+3)))<0.01,"OK","ERRORE")} | C15: Salari e Stipendi: Piano = foglio
A16: 7 | B16: {=IF(ABS(SUM('Piano Finanziario'!D15:S15)-SUMPRODUCT((Utenze!D3:Y3)*(COLUMN(Utenze!D3:Y3)>=MATCH('Piano Finanziario'!D2,Utenze!D2:Y2,0)+3)))<0.01,"OK","ERRORE")} | C16: Utenze: Piano = foglio
A17: 8 | B17: {=IF(ABS(SUM('Piano Finanziario'!D16:S16)-SUMPRODUCT(('Materie Prime-Conumo '!D3:Y3)*(COLUMN('Materie Prime-Conumo '!D3:Y3)>=MATCH('Piano Finanziario'!D2,'Materie Prime-Conumo '!D2:Y2,0)+3)))<0.01,"OK","ERRORE")} | C17: Materie Prime: Piano = foglio
A18: 9 | B18: {=IF(ABS(SUM('Piano Finanziario'!D17:S17)-SUMPRODUCT(('Tasse e Imposte'!D3:Y3)*(COLUMN('Tasse e Imposte'!D3:Y3)>=MATCH('Piano Finanziario'!D2,'Tasse e Imposte'!D2:Y2,0)+3)))<0.01,"OK","ERRORE")} | C18: Tasse e Imposte: Piano = foglio
A19: 10 | B19: {=IF(ABS(SUM('Piano Finanziario'!D18:S18)-SUMPRODUCT(('Mutui e Finaziamenti'!D3:Y3)*(COLUMN('Mutui e Finaziamenti'!D3:Y3)>=MATCH('Piano Finanziario'!D2,'Mutui e Finaziamenti'!D2:Y2,0)+3)))<0.01,"OK","ERRORE")} | C19: Mutui e Finanziamenti: Piano = foglio
A20: 11 | B20: {=IF(ABS(SUM('Piano Finanziario'!D19:S19)-SUMPRODUCT((Consulenze!D3:Y3)*(COLUMN(Consulenze!D3:Y3)>=MATCH('Piano Finanziario'!D2,Consulenze!D2:Y2,0)+3)))<0.01,"OK","ERRORE")} | C20: Consulenze: Piano = foglio
A21: 12 | B21: {=IF(ABS(SUM('Piano Finanziario'!D20:S20)-SUMPRODUCT(('Godimento Beni di Terzi'!D3:Y3)*(COLUMN('Godimento Beni di Terzi'!D3:Y3)>=MATCH('Piano Finanziario'!D2,'Godimento Beni di Terzi'!D2:Y2,0)+3)))<0.01,"OK","ERRORE")} | C21: Godimento Beni di Terzi: Piano = foglio
A22: 13 | B22: {=IF(ABS(SUM('Piano Finanziario'!D21:S21)-SUMPRODUCT((' Varie ed Eventuali'!D3:Y3)*(COLUMN(' Varie ed Eventuali'!D3:Y3)>=MATCH('Piano Finanziario'!D2,' Varie ed Eventuali'!D2:Y2,0)+3)))<0.01,"OK","ERRORE")} | C22: Varie ed Eventuali: Piano = foglio
A23: 14 | B23: {=IF(ABS(SUM('Piano Finanziario'!D22:S22)-SUMPRODUCT(('Canoni e servizi'!D3:Y3)*(COLUMN('Canoni e servizi'!D3:Y3)>=MATCH('Piano Finanziario'!D2,'Canoni e servizi'!D2:Y2,0)+3)))<0.01,"OK","ERRORE")} | C23: Canoni e servizi: Piano = foglio
A25: SALDI
A26: 15 | B26: =IF(ABS('Piano Finanziario'!D3-'Piano Finanziario'!C35)<0.01,"OK","ERRORE") | C26: Saldo iniziale = Totale Banche
A27: 16 | B27: {=IF(SUMPRODUCT(ABS('Piano Finanziario'!D38:S38-('Piano Finanziario'!D3:S3+'Piano Finanziario'!D29:S29+'Piano Finanziario'!D35:S35)))<0.01,"OK","ERRORE")} | C27: Saldo Periodo = Prec + CF + Banche (ogni mese)
A28: 17 | B28: {=IF(SUMPRODUCT(ABS('Piano Finanziario'!D46:S46-('Piano Finanziario'!D38:S38+'Piano Finanziario'!D44:S44)))<0.01,"OK","ERRORE")} | C28: CF con Affidamenti = Saldo + Affidamenti
A30: FOGLI INTERNI
A31: 18 | B31: =IF(ABS('Salari e Stipendi'!C3-SUM('Salari e Stipendi'!D3:Y3))<0.01,"OK","ERRORE") | C31: Salari: totale = somma mesi
A32: 19 | B32: =IF(ABS(Utenze!C3-SUM(Utenze!D3:Y3))<0.01,"OK","ERRORE") | C32: Utenze: totale = somma mesi
A33: 20 | B33: =IF(ABS('Tasse e Imposte'!C3-SUM('Tasse e Imposte'!D3:Y3))<0.01,"OK","ERRORE") | C33: Tasse: totale = somma mesi
A34: 21 | B34: =IF(ABS('Mutui e Finaziamenti'!C3-SUM('Mutui e Finaziamenti'!D3:Y3))<0.01,"OK","ERRORE") | C34: Mutui: totale = somma mesi
A35: 22 | B35: =IF(ABS(Consulenze!C3-SUM(Consulenze!D3:Y3))<0.01,"OK","ERRORE") | C35: Consulenze: totale = somma mesi
A36: 23 | B36: =IF(ABS(' Varie ed Eventuali'!C3-SUM(' Varie ed Eventuali'!D3:Y3))+ABS('Canoni e servizi'!C3-SUM('Canoni e servizi'!D3:Y3))+ABS('Godimento Beni di Terzi'!C3-SUM('Godimento Beni di Terzi'!D3:Y3))+ABS('Materie Prime-Conumo '!C3-SUM('Materie Prime-Conumo '!D3:Y3))<0.01,"OK","ERRORE") | C36: Varie + Canoni + Godimento + Mat.Prime: totale = somma
A38: ══════════════════════════════
B39: =IF(COUNTIF(B6:B36,"ERRORE")=0,"✓ TUTTI I CONTROLLI OK (×"&COUNTIF(B6:B36,"OK")&" verifiche)","✗ "&COUNTIF(B6:B36,"ERRORE")&" ERRORI su "&(COUNTIF(B6:B36,"OK")+COUNTIF(B6:B36,"ERRORE"))&" verifiche")

Sheet Piano Finanziario
A1: INTUR | C1: DATA RILEVAZ | D1: 2026 | N1: 2027
C2: 31/08/2026 | D2: MARZO | E2: APRILE | F2: MAGGIO | G2: GIUGNO | H2: LUGLIO | I2: AGOSTO | J2: SETTEMBRE | K2: OTTOBRE | L2: NOVEMBRE | M2: DICEMBRE | N2: GENNAIO | O2: FEBBRAIO | P2: MARZO | Q2: APRILE | R2: MAGGIO | S2: GIUGNO
A3: SALDO MESE PRECED. | D3: =C35 | E3: =D38 | F3: =E38 | G3: =F38 | H3: =G38 | I3: =H38 | J3: =I38 | K3: =J38 | L3: =K38 | ... S3: =R38
A5: Fitto Hotel | J5: 244000 | K5: 0 | M5: 488000 | S5: 244000
A6: Fitto AR
A7: Entrate Residence | D7: 0 | J7: 0 | K7: 0 | L7: 0 | M7: 0
A8: Ribaltamento Costi a Orti
A9: Entrate Farmacia | J9: 3750 | K9: 3750 | L9: 3750 | M9: 3750
A10: Entrate Spiaggia | J10: 35000
A12: TOTALE ENTRATE | C12: =SUM(C5:C9) | D12: =SUM(D5:D11) | E12: =SUM(E5:E11) | F12: =SUM(F5:F11) | G12: =SUM(G5:G11) | H12: =SUM(H5:H11) | I12: =SUM(I5:I11) | J12: =SUM(J5:J11) | K12: =SUM(K5:K11) | ... S12: =SUM(S5:S11)
A14: Salari e Stipendi | D14: ='Salari e Stipendi'!J3 | E14: ='Salari e Stipendi'!K3 | F14: ='Salari e Stipendi'!L3 | G14: ='Salari e Stipendi'!M3 | H14: ='Salari e Stipendi'!N3 | I14: ='Salari e Stipendi'!O3 | J14: ='Salari e Stipendi'!P3 | K14: ='Salari e Stipendi'!Q3 | ... S14: ='Salari e Stipendi'!Y3
A15: Utenze | D15: =Utenze!J3 | E15: =Utenze!K3 | F15: =Utenze!L3 | G15: =Utenze!M3 | H15: =Utenze!N3 | I15: =Utenze!O3 | J15: =Utenze!P3 | K15: =Utenze!Q3 | ... S15: =Utenze!Y3
A16: Materie Prime/Consumo | D16: ='Materie Prime-Conumo '!J3 | E16: ='Materie Prime-Conumo '!K3 | F16: ='Materie Prime-Conumo '!L3 | G16: ='Materie Prime-Conumo '!M3 | H16: ='Materie Prime-Conumo '!N3 | I16: ='Materie Prime-Conumo '!O3 | J16: ='Materie Prime-Conumo '!P3 | K16: ='Materie Prime-Conumo '!Q3 | ... S16: ='Materie Prime-Conumo '!Y3
A17: Tasse e Imposte | D17: ='Tasse e Imposte'!J3 | E17: ='Tasse e Imposte'!K3 | F17: ='Tasse e Imposte'!L3 | G17: ='Tasse e Imposte'!M3 | H17: ='Tasse e Imposte'!N3 | I17: ='Tasse e Imposte'!O3 | J17: ='Tasse e Imposte'!P3 | K17: ='Tasse e Imposte'!Q3 | ... S17: ='Tasse e Imposte'!Y3
A18: Mutui e Finaziamenti | D18: ='Mutui e Finaziamenti'!J3 | E18: ='Mutui e Finaziamenti'!K3 | F18: ='Mutui e Finaziamenti'!L3 | G18: ='Mutui e Finaziamenti'!M3 | H18: ='Mutui e Finaziamenti'!N3 | I18: ='Mutui e Finaziamenti'!O3 | J18: ='Mutui e Finaziamenti'!P3 | K18: ='Mutui e Finaziamenti'!Q3 | ... S18: ='Mutui e Finaziamenti'!Y3
A19: Consulenze | D19: =Consulenze!J3 | E19: =Consulenze!K3 | F19: =Consulenze!L3 | G19: =Consulenze!M3 | H19: =Consulenze!N3 | I19: =Consulenze!O3 | J19: =Consulenze!P3 | K19: =Consulenze!Q3 | ... S19: =Consulenze!Y3
A20: Godimento Benidi Terzi | D20: ='Godimento Beni di Terzi'!J3 | E20: ='Godimento Beni di Terzi'!K3 | F20: ='Godimento Beni di Terzi'!L3 | G20: ='Godimento Beni di Terzi'!M3 | H20: ='Godimento Beni di Terzi'!N3 | I20: ='Godimento Beni di Terzi'!O3 | J20: ='Godimento Beni di Terzi'!P3 | K20: ='Godimento Beni di Terzi'!Q3 | ... S20: ='Godimento Beni di Terzi'!Y3
A21: Varie ed Eventuali | D21: =' Varie ed Eventuali'!J3 | E21: =' Varie ed Eventuali'!K3 | F21: =' Varie ed Eventuali'!L3 | G21: =' Varie ed Eventuali'!M3 | H21: =' Varie ed Eventuali'!N3 | I21: =' Varie ed Eventuali'!O3 | J21: =' Varie ed Eventuali'!P3 | K21: =' Varie ed Eventuali'!Q3 | ... S21: =' Varie ed Eventuali'!Y3
A22: Canoni e servizi | D22: ='Canoni e servizi'!J3 | E22: ='Canoni e servizi'!K3 | F22: ='Canoni e servizi'!L3 | G22: ='Canoni e servizi'!M3 | H22: ='Canoni e servizi'!N3 | I22: ='Canoni e servizi'!O3 | J22: ='Canoni e servizi'!P3 | K22: ='Canoni e servizi'!Q3 | ... S22: ='Canoni e servizi'!Y3
A23: Caparre da girocantare aOrti | C23: =Nota!B4 | D23: 0 | E23: 0 | F23: 0 | G23: 0 | H23: 0 | I23: 0 | J23: 0 | K23: 0 | L23: 0 | M23: 0
A27: TOTALE USCITE | D27: =SUM(D14:D26) | E27: =SUM(E14:E26) | F27: =SUM(F14:F26) | G27: =SUM(G14:G26) | H27: =SUM(H14:H26) | I27: =SUM(I14:I26) | J27: =SUM(J14:J26) | K27: =SUM(K14:K26) | ... S27: =SUM(S14:S26)
A29: CASH FLOW | C29: =C12-C27 | D29: =D12-D27 | E29: =E12-E27 | F29: =F12-F27 | G29: =G12-G27 | H29: =H12-H27 | I29: =I12-I27 | J29: =J12-J27 | ... S29: =S12-S27
A31: Saldo Banca Sella | C31: 42651.06
A32: Saldo MPS | C32: 166377.42
A33: Saldo Intesa | C33: 3093.86
A35: TOTALE BANCHE | C35: =SUM(C31:C34) | D35: =SUM(D31:D34) | E35: =SUM(E31:E34) | F35: =SUM(F31:F34) | G35: =SUM(G31:G34) | H35: =SUM(H31:H34) | I35: =SUM(I31:I34) | J35: =SUM(J31:J34) | ... S35: =SUM(S31:S34)
A38: Saldo di Periodo/Proiettato | C38: =C35 | D38: =D3+(D29+D35) | E38: =E3+(E29+E35) | F38: =F3+(F29+F35) | G38: =G3+(G29+G35) | H38: =H3+(H29+H35) | I38: =I3+(I29+I35) | J38: =J3+(J29+J35) | K38: =K3+(K29+K35) | ... S38: =S3+(S29+S35)
A40: Affidamento Sella | C40: 150000 | D40: 150000 | E40: 150000 | F40: 150000 | G40: 150000 | H40: 150000 | I40: 150000 | J40: 150000 | K40: 100000 | L40: 100000 | M40: 100000
A44: TOTALE AFFIDAMENTI | C44: =SUM(C40:C43) | D44: =SUM(D40:D43) | E44: =SUM(E40:E43) | F44: =SUM(F40:F43) | G44: =SUM(G40:G43) | H44: =SUM(H40:H43) | I44: =SUM(I40:I43) | J44: =SUM(J40:J43) | ... S44: =SUM(S40:S43)
A46: CASH FLOW CON AFFID. | C46: =C38+C44 | D46: =D38+D44 | E46: =E38+E44 | F46: =F38+F44 | G46: =G38+G44 | H46: =H38+H44 | I46: =I38+I44 | J46: =J38+J44 | ... S46: =S38+S44

Sheet Salari e Stipendi
D1: 2025 | H1: 2026 | T1: 2027
D2: SETTEMBRE | E2: OTTOBRE | F2: NOVEMBRE | G2: DICEMBRE | H2: GENNAIO | I2: FEBBRAIO | J2: MARZO | K2: APRILE | L2: MAGGIO | M2: GIUGNO | N2: LUGLIO | O2: AGOSTO | P2: SETTEMBRE | Q2: OTTOBRE | R2: NOVEMBRE | S2: DICEMBRE | T2: GENNAIO | U2: FEBBRAIO | V2: MARZO | W2: APRILE | X2: MAGGIO | Y2: GIUGNO
B3: Salari e Stipendi | C3: =SUM(D3:Y3) | D3: =SUM(D4:D134) | E3: =SUM(E4:E134) | F3: =SUM(F4:F134) | G3: =SUM(G4:G134) | H3: =SUM(H4:H134) | I3: =SUM(I4:I134) | J3: =SUM(J4:J134) | K3: =SUM(K4:K134) | ... Y3: =SUM(Y4:Y134)
B4: Salari | C4: =SUM(D4:Y4) | F4: 0 | G4: 0 | P4: 11376.14 | Q4: 9000 | R4: 10000 | S4: 5000 | T4: 2800 | U4: 2700 | V4: 2700 | W4: 2700 | X4: 2700 | Y4: 2700
B5: F24 | F5: 0 | G5: 0 | P5: 5000 | Q5: 5000 | R5: 5000 | S5: 3000 | T5: 1350 | U5: 1400 | V5: 1400 | W5: 1200 | X5: 1212 | Y5: 1300
A6: 73 | B6: DELLA PIETRA STEFANO | P6: 5100

Sheet Utenze
D1: 2025 | H1: 2026 | T1: 2027
D2: SETTEMBRE | E2: OTTOBRE | F2: NOVEMBRE | G2: DICEMBRE | H2: GENNAIO | I2: FEBBRAIO | J2: MARZO | K2: APRILE | L2: MAGGIO | M2: GIUGNO | N2: LUGLIO | O2: AGOSTO | P2: SETTEMBRE | Q2: OTTOBRE | R2: NOVEMBRE | S2: DICEMBRE | T2: GENNAIO | U2: FEBBRAIO | V2: MARZO | W2: APRILE | X2: MAGGIO | Y2: GIUGNO
B3: Utenze | C3: =SUM(D3:Y3) | D3: =SUM(D4:D133) | E3: =SUM(E4:E133) | F3: =SUM(F4:F133) | G3: =SUM(G4:G133) | H3: =SUM(H4:H133) | I3: =SUM(I4:I133) | J3: =SUM(J4:J133) | K3: =SUM(K4:K133) | ... Y3: =SUM(Y4:Y133)
A4: RID | B4: Energia elettrica | C4: =SUM(D4:Y4) | F4: 0 | G4: 0 | P4: 850 | Q4: 900
A5: RID | B5: Gas | C5: =SUM(D5:Y5) | F5: 0
B6: Ausino - rateizzo | C6: =SUM(D6:Y6) | F6: 0 | P6: 8605.46 | Q6: 355.25
A7: RID | B7: Vodafone (da ribaltare) | C7: =SUM(D7:Y7) | P7: 109.8
A8: 1592 | B8: FASTWEB SPA | C8: =SUM(D8:Y8) | P8: 1537.2
A9: 30 | B9: 4G ENERGIA SRL | C9: =SUM(D9:Y9) | Q9: 1912.43
C10: =SUM(D10:Y10)
C11: =SUM(D11:Y11)
C12: =SUM(D12:Y12)
C13: =SUM(D13:Y13)
C14: =SUM(D14:Y14)
C15: =SUM(D15:Y15)
C16: =SUM(D16:Y16)
C17: =SUM(D17:Y17)
C18: =SUM(D18:Y18)
C19: =SUM(D19:Y19)
C20: =SUM(D20:Y20)
C21: =SUM(D21:Y21)
... C61: =SUM(D61:Y61)

Sheet Materie Prime-Conumo 
D1: 2025 | H1: 2026 | T1: 2027
D2: SETTEMBRE | E2: OTTOBRE | F2: NOVEMBRE | G2: DICEMBRE | H2: GENNAIO | I2: FEBBRAIO | J2: MARZO | K2: APRILE | L2: MAGGIO | M2: GIUGNO | N2: LUGLIO | O2: AGOSTO | P2: SETTEMBRE | Q2: OTTOBRE | R2: NOVEMBRE | S2: DICEMBRE | T2: GENNAIO | U2: FEBBRAIO | V2: MARZO | W2: APRILE | X2: MAGGIO | Y2: GIUGNO
B3: Materie Prime e Consumo | C3: =SUM(D3:Y3) | D3: =SUM(D4:D164) | E3: =SUM(E4:E164) | F3: =SUM(F4:F164) | G3: =SUM(G4:G164) | H3: =SUM(H4:H164) | I3: =SUM(I4:I164) | J3: =SUM(J4:J164) | K3: =SUM(K4:K164) | ... Y3: =SUM(Y4:Y164)
A4: 48 | B4: B&G Di Palo | C4: =SUM(D4:Y4) | D4: 0 | F4: 0 | G4: 0 | P4: 75.25
A5: 596 | B5: BABBI SRL | C5: =SUM(D5:Y5) | P5: 175.2
B6: J.F. Amonn | C6: =SUM(D6:Y6)
A7: 325 | B7: ALFERA S.R.L. | C7: =SUM(D7:Y7)
A8: 158 | B8: GALLO GIOVANNI & C. SNC | C8: =SUM(D8:Y8) | P8: 164.52
A9: 142 | B9: GENERAL BEVERAGE S.R.L. | C9: =SUM(D9:Y9)
C10: =SUM(D10:Y10)
A11: 1273.38 | B11: CoIrEs SRL | C11: =SUM(D11:Y11) | P11: 1273.38
B12: Creative Idea Snc | C12: =SUM(D12:Y12)
B13: De Riso | C13: =SUM(D13:Y13) | P13: 27
B14: EURO GROUP NETWORK S.R.L. | C14: =SUM(D14:Y14)
B15: Foraggio Srl | C15: =SUM(D15:Y15)
B16: IDRO-TOP SRL | C16: =SUM(D16:Y16) | P16: 64.68
B17: INDEL B | C17: =SUM(D17:Y17)
B18: Locali d'autore | C18: =SUM(D18:Y18)
B19: Mediterraneo | C19: =SUM(D19:Y19) | F19: 0 | G19: 0
B20: Ninni | C20: =SUM(D20:Y20) | F20: 0 | G20: 0
B21: Oceano Distribuzione | C21: =SUM(D21:Y21)
B22: Pasticceria Trieste | C22: =SUM(D22:Y22)
B23: Rastrelli Antonia | C23: =SUM(D23:Y23) | P23: 55.33
A24: 412036.53 | B24: Panorama Company Srl | C24: =SUM(D24:Y24)
B25: Paravia | C25: =SUM(D25:Y25)
B26: Primavera Servizi Srl | C26: =SUM(D26:Y26)
B27: Giardiniello | C27: =SUM(D27:Y27)
A28: 45440 | B28: Tecno Campania | C28: =SUM(D28:Y28)
B29: Vulaj (Ceramica) | C29: =SUM(D29:Y29) | F29: 0 | G29: 0 | P29: 45.01

Sheet Tasse e Imposte
D1: 2025 | H1: 2026 | T1: 2027
D2: SETTEMBRE | E2: OTTOBRE | F2: NOVEMBRE | G2: DICEMBRE | H2: GENNAIO | I2: FEBBRAIO | J2: MARZO | K2: APRILE | L2: MAGGIO | M2: GIUGNO | N2: LUGLIO | O2: AGOSTO | P2: SETTEMBRE | Q2: OTTOBRE | R2: NOVEMBRE | S2: DICEMBRE | T2: GENNAIO | U2: FEBBRAIO | V2: MARZO | W2: APRILE | X2: MAGGIO | Y2: GIUGNO
B3: Tasse e Imposte | C3: =SUM(D3:Y3) | D3: =SUM(D4:D131) | E3: =SUM(E4:E131) | F3: =SUM(F4:F131) | G3: =SUM(G4:G131) | H3: =SUM(H4:H131) | I3: =SUM(I4:I131) | J3: =SUM(J4:J131) | K3: =SUM(K4:K131) | ... Y3: =SUM(Y4:Y131)
B4: IMU | C4: =SUM(D4:Y4) | G4: 0 | Y4: 34365
B5: I ACCONTO IMPOSTE | C5: =SUM(D5:Y5) | F5: 0
B6: TARI | C6: =SUM(F6:S6)
B7: IVA | C7: =SUM(E7:S7) | F7: 0 | G7: 0 | P7: 800 | Q7: 800 | R7: 800
B8: IRES | C8: =SUM(E8:S8) | F8: 0 | R8: 28000
B9: IRAP | C9: =SUM(E9:S9) | F9: 0
B10: AFFRANCAMENTO | C10: =SUM(E10:S10) | Y10: 200000
B11: ARRETRATO IMPOSTE | C11: =SUM(E11:S11)
A12: 36000 | B12: ARRETRATO IMU | C12: =SUM(D12:Y12) | F12: 0 | G12: 0
B13: Ritenute professionisti (1040) | C13: =SUM(D13:Y13)
A14: 781 | B14: COMUNE DI MAIORI | C14: =SUM(D14:Y14) | P14: 34525.4
C15: =SUM(D15:Y15)
C16: =SUM(D16:Y16)
C17: =SUM(D17:Y17)
C18: =SUM(D18:Y18)
C19: =SUM(D19:Y19)
C20: =SUM(D20:Y20)
C21: =SUM(D21:Y21)
C22: =SUM(D22:Y22)
C23: =SUM(D23:Y23)
C24: =SUM(D24:Y24)
C25: =SUM(D25:Y25)
C26: =SUM(D26:Y26)
... C59: =SUM(D59:Y59)

Sheet Mutui e Finaziamenti
D1: 2025 | H1: 2026 | T1: 2027
D2: SETTEMBRE | E2: OTTOBRE | F2: NOVEMBRE | G2: DICEMBRE | H2: GENNAIO | I2: FEBBRAIO | J2: MARZO | K2: APRILE | L2: MAGGIO | M2: GIUGNO | N2: LUGLIO | O2: AGOSTO | P2: SETTEMBRE | Q2: OTTOBRE | R2: NOVEMBRE | S2: DICEMBRE | T2: GENNAIO | U2: FEBBRAIO | V2: MARZO | W2: APRILE | X2: MAGGIO | Y2: GIUGNO
B3: Mutui e Finanaziamenti | C3: =SUM(D3:Y3) | D3: =SUM(D4:D134) | E3: =SUM(E4:E134) | F3: =SUM(F4:F134) | G3: =SUM(G4:G134) | H3: =SUM(H4:H134) | I3: =SUM(I4:I134) | J3: =SUM(J4:J134) | K3: =SUM(K4:K134) | ... Y3: =SUM(Y4:Y134)
B4: Mutuo Banca Intesa | C4: =SUM(D4:Y4) | F4: 0 | P4: 9000 | Q4: 9000 | R4: 9000 | S4: 9000 | T4: 9000 | U4: 9000 | V4: 9000 | W4: 9000 | X4: 9000 | Y4: 9000
B5: Finanziamento Sella | C5: =SUM(D5:Y5) | F5: 0
B6: Finanziamento MPS 75K | C6: =SUM(D6:Y6) | F6: 0 | P6: 1388.48 | Q6: 1388.48 | R6: 1388.48 | S6: 1388.48 | T6: 1388.48 | U6: 1388.48 | V6: 1388.48 | W6: 1388.48 | X6: 1388.48 | Y6: 1388.48
B7: Finanziamento MPS 1200K | C7: =SUM(D7:Y7) | P7: 3500 | Q7: 3500 | R7: 3500 | S7: 3500 | T7: 3500 | U7: 13000 | V7: 13000 | W7: 13000 | X7: 13000 | Y7: 13000
C8: =SUM(D8:Y8)
C9: =SUM(D9:Y9)
C10: =SUM(D10:Y10)
C11: =SUM(D11:Y11)
C12: =SUM(D12:Y12)
C13: =SUM(D13:Y13)
C14: =SUM(D14:Y14)
C15: =SUM(D15:Y15)
C16: =SUM(D16:Y16)
C17: =SUM(D17:Y17)
C18: =SUM(D18:Y18)
C19: =SUM(D19:Y19)
... C62: =SUM(D62:Y62)

Sheet Consulenze
D1: 2025 | H1: 2026 | T1: 2027
D2: SETTEMBRE | E2: OTTOBRE | F2: NOVEMBRE | G2: DICEMBRE | H2: GENNAIO | I2: FEBBRAIO | J2: MARZO | K2: APRILE | L2: MAGGIO | M2: GIUGNO | N2: LUGLIO | O2: AGOSTO | P2: SETTEMBRE | Q2: OTTOBRE | R2: NOVEMBRE | S2: DICEMBRE | T2: GENNAIO | U2: FEBBRAIO | V2: MARZO | W2: APRILE | X2: MAGGIO | Y2: GIUGNO
B3: Consulenze | C3: =SUM(D3:Y3) | D3: =SUM(D4:D134) | E3: =SUM(E4:E134) | F3: =SUM(F4:F134) | G3: =SUM(G4:G134) | H3: =SUM(H4:H134) | I3: =SUM(I4:I134) | J3: =SUM(J4:J134) | K3: =SUM(K4:K134) | ... Y3: =SUM(Y4:Y134)
B4: Consulenza del lavoro | C4: =SUM(D4:Y4) | F4: 0 | G4: 0 | P4: 700 | R4: 500 | U4: 1540 | V4: 400 | X4: 600
B5: Consulenza fiscale | C5: =SUM(D5:Y5) | P5: 2000 | S5: 2000 | V5: 2500 | Y5: 2000
B6: Consulenza legale | C6: =SUM(D6:Y6)
B7: Prev. Consulenze Legali | C7: =SUM(D7:Y7)
B8: ALDEN | C8: =SUM(D8:Y8) | P8: 244
B9: Revisore - Ferrigno | C9: =SUM(D9:Y9) | W9: 4162
B10: Cons. Marketing - Travaglini Armando | C10: =SUM(D10:Y10)
B11: DG NETWORK | C11: =SUM(D11:Y11)
B12: Geologo Antonio Apicella | C12: =SUM(D12:Y12) | P12: 1015.04
A13: 1027 | B13: CAFARELLI MASSIMILIANO | C13: =SUM(D13:Y13) | P13: 30
B14: CSW Engineering s.r.l | C14: =SUM(D14:Y14)
B15: Amalia Pisacane | C15: =SUM(D15:Y15) | P15: 40983.36
A16: 921 | B16: Il Centro C.S.C. Srl | C16: =SUM(D16:Y16) | P16: 688.2
A17: 645 | B17: D'Aiuto (legale) | C17: =SUM(D17:Y17) | P17: 6343.98
A18: 41 | B18: Giordano Associati S.r.l Socio Unico | C18: =SUM(D18:Y18) | Q18: 819.88
A19: 649 | B19: Guariniello Lorenzo | C19: =SUM(D19:Y19) | P19: 2618.56
C20: =SUM(D20:Y20)
C21: =SUM(D21:Y21)
C22: =SUM(D22:Y22)
C23: =SUM(D23:Y23)
C24: =SUM(D24:Y24)
C25: =SUM(D25:Y25)
C26: =SUM(D26:Y26)
C27: =SUM(D27:Y27)
C28: =SUM(D28:Y28)
C29: =SUM(D29:Y29)
C30: =SUM(D30:Y30)
C31: =SUM(D31:Y31)
... C62: =SUM(D62:Y62)

Sheet Godimento Beni di Terzi
D1: 2025 | H1: 2026 | T1: 2027
D2: SETTEMBRE | E2: OTTOBRE | F2: NOVEMBRE | G2: DICEMBRE | H2: GENNAIO | I2: FEBBRAIO | J2: MARZO | K2: APRILE | L2: MAGGIO | M2: GIUGNO | N2: LUGLIO | O2: AGOSTO | P2: SETTEMBRE | Q2: OTTOBRE | R2: NOVEMBRE | S2: DICEMBRE | T2: GENNAIO | U2: FEBBRAIO | V2: MARZO | W2: APRILE | X2: MAGGIO | Y2: GIUGNO
B3: Godimento Beni di Terzi | C3: =SUM(D3:Y3) | D3: =SUM(D4:D134) | E3: =SUM(E4:E134) | F3: =SUM(F4:F134) | G3: =SUM(G4:G134) | H3: =SUM(H4:H134) | I3: =SUM(I4:I134) | J3: =SUM(J4:J134) | K3: =SUM(K4:K134) | ... Y3: =SUM(Y4:Y134)
A4: 783 | B4: DELLA PIERTA PAOLA | C4: =SUM(D4:Y4) | P4: 4650
A5: 782 | B5: DELLA PIETRA ANNAMARIA | C5: =SUM(D5:Y5) | P5: 4650
C6: =SUM(D6:Y6)
C7: =SUM(D7:Y7)
C8: =SUM(D8:Y8)
C9: =SUM(D9:Y9)
C10: =SUM(D10:Y10)
C11: =SUM(D11:Y11)
C12: =SUM(D12:Y12)
C13: =SUM(D13:Y13)
C14: =SUM(D14:Y14)
C15: =SUM(D15:Y15)
C16: =SUM(D16:Y16)
C17: =SUM(D17:Y17)
... C62: =SUM(D62:Y62)

Sheet Canoni e servizi
D1: 2025 | H1: 2026 | T1: 2027
D2: SETTEMBRE | E2: OTTOBRE | F2: NOVEMBRE | G2: DICEMBRE | H2: GENNAIO | I2: FEBBRAIO | J2: MARZO | K2: APRILE | L2: MAGGIO | M2: GIUGNO | N2: LUGLIO | O2: AGOSTO | P2: SETTEMBRE | Q2: OTTOBRE | R2: NOVEMBRE | S2: DICEMBRE | T2: GENNAIO | U2: FEBBRAIO | V2: MARZO | W2: APRILE | X2: MAGGIO | Y2: GIUGNO
B3: Canoni e servizi | C3: =SUM(D3:Y3) | D3: =SUM(D4:D132) | E3: =SUM(E4:E132) | F3: =SUM(F4:F132) | G3: =SUM(G4:G132) | H3: =SUM(H4:H132) | I3: =SUM(I4:I132) | J3: =SUM(J4:J132) | K3: =SUM(K4:K132) | ... Y3: =SUM(Y4:Y132)
B4: Pin App | C4: =SUM(D4:Y4) | F4: 0 | H4: 0
B5: Spiagge | C5: =SUM(D5:Y5)
B6: Spese Bancarie | C6: =SUM(D6:Y6)
B7: Banca sella - canone e-commerce RID | C7: =SUM(D7:Y7)
A8: 1558 | B8: Oliva Coperture | C8: =SUM(D8:Y8)
A9: 15 | B9: Altamira Srl | C9: =SUM(D9:Y9)
A10: 52 | B10: Aruba S.p.A. | C10: =SUM(D10:Y10)
A11: 16 | B11: SOFTWARE STUDIO S.R.L. | C11: =SUM(D11:Y11) | P11: 475.8
B12: Amalfi Web | C12: =SUM(D12:Y12)
B13: Commissioni Pos | C13: =SUM(D13:Y13)
A14: 1069 | B14: TOPWHITE DI DANIELE RAVELLI | C14: =SUM(D14:Y14)
C15: =SUM(D15:Y15)
C16: =SUM(D16:Y16)
C17: =SUM(D17:Y17)
C18: =SUM(D18:Y18)
C19: =SUM(D19:Y19)
C20: =SUM(D20:Y20)
C21: =SUM(D21:Y21)
C22: =SUM(D22:Y22)
C23: =SUM(D23:Y23)
C24: =SUM(D24:Y24)
C25: =SUM(D25:Y25)
C26: =SUM(D26:Y26)
... C61: =SUM(D61:Y61)

Sheet  Varie ed Eventuali
D1: 2025 | H1: 2026 | T1: 2027
D2: SETTEMBRE | E2: OTTOBRE | F2: NOVEMBRE | G2: DICEMBRE | H2: GENNAIO | I2: FEBBRAIO | J2: MARZO | K2: APRILE | L2: MAGGIO | M2: GIUGNO | N2: LUGLIO | O2: AGOSTO | P2: SETTEMBRE | Q2: OTTOBRE | R2: NOVEMBRE | S2: DICEMBRE | T2: GENNAIO | U2: FEBBRAIO | V2: MARZO | W2: APRILE | X2: MAGGIO | Y2: GIUGNO
C3: =SUM(D3:Y3) | D3: =SUM(D5:D135) | E3: =SUM(E5:E135) | F3: =SUM(F5:F135) | G3: =SUM(G5:G135) | H3: =SUM(H5:H135) | I3: =SUM(I5:I135) | J3: =SUM(J5:J135) | K3: =SUM(K5:K135) | L3: =+L4+L5+L6+L7+L8+L9+L10+L12+L13+L14+L15+L16+L17+L18 | M3: =+M4+M5+M6+M7+M8+M9+M10+M12+M13+M14+M15+M16+M17+M18 | N3: =+N4+N5+N6+N7+N8+N9+N10+N12+N13+N14+N15+N16+N17+N18 | O3: =+O4+O5+O6+O7+O8+O9+O10+O12+O13+O14+O15+O16+O17+O18 | P3: =+P4+P5+P6+P7+P8+P9+P10+P12+P13+P14+P15+P16+P17+P18 | Q3: =+Q4+Q5+Q6+Q7+Q8+Q9+Q10+Q12+Q13+Q14+Q15+Q16+Q17+Q18 | R3: =+R4+R5+R6+R7+R8+R9+R10+R12+R13+R14+R15+R16+R17+R18 | S3: =+S4+S5+S6+S7+S8+S9+S10+S12+S13+S14+S15+S16+S17+S18 | ... Y3: =+Y4+Y5+Y6+Y7+Y8+Y9+Y10+Y12+Y13+Y14+Y15+Y16+Y17+Y18
B4: Variee ed Eventuali | P4: 15000 | Q4: 15000 | R4: 15000 | S4: 15000
A5: 266 | B5: B & T SpA | C5: =SUM(D5:Y5) | F5: 0
A6: 1734 | B6: Ce.Di.S. srl | C6: =SUM(D6:Y6)
A7: 716 | B7: CERAMICA D'ARTE SICIGNANO SRL | C7: =SUM(D7:Y7) | P7: 26146.37
A8: 1640 | B8: Domus Tappezzeria D'Arredo S.R.L. | C8: =SUM(D8:Y8)
A9: 1607 | B9: LAUDATO GRU DI LAUDATO FRANCESCO | C9: =SUM(D9:Y9)
A10: 734 | B10: LEONE S.R.L. | C10: =SUM(D10:Y10)
A11: 1008 | B11: MIELE GIUSEPPE E FIGLI SPA | C11: =SUM(D11:Y11)
A12: 1672 | B12: OMBRELLONI LETTINI ITALIA S.R.L. | C12: =SUM(D12:Y12)
A13: 64 | B13: PARAVIA ELEVATORS SRL | C13: =SUM(D13:Y13)
A14: 863 | B14: SALA GIANPIERO | C14: =SUM(D14:Y14) | P14: 88139.3
A15: 121 | B15: Santelia Luigi | C15: =SUM(D15:Y15) | Q15: 15000
A16: 1214 | B16: VDA GROUP S.p.A. a socio unico | C16: =SUM(D16:Y16)
A17: 1662 | B17: Indel B Spa | C17: =SUM(D17:Y17)
A18: 1054 | B18: O.V.I.T. SRL | P18: 171
A19: 1034 | B19: ORIL SRL | P19: 66.08
A20: 777 | B20: ACCONCIANGIOCO & MANADRA SNC | P20: 12420
A21: 412 | B21: Alberto D Urso S.a.s. di Tecla Apicella | P21: 334.87
A22: 779 | B22: FORNITORE ANTE 2024 | P22: 54039.74
A23: 1162 | B23: STE elettrico | Q23: 49500

Sheet Nota
A1: Debiti non inseriti nel piano
A3: Fornitore | B3: Importo
A4: Caparre da girocantare aOrti | B4: 130556.57
A5: SDP | B5: 33600
A7: Panorama Company | B7: 412036.53

Sheet DA MAPPARE
A1: Fornitori NON mappati in d_fornitori.csv — assegnare una voce (hotelops fornitori) e rigenerare
A2: Cod | B2: Nome (da export) | C2: GENNAIO | D2: FEBBRAIO | E2: MARZO | F2: APRILE | G2: MAGGIO | H2: GIUGNO | I2: LUGLIO | J2: AGOSTO | K2: SETTEMBRE | L2: OTTOBRE | M2: NOVEMBRE | N2: DICEMBRE

Sheet ESCLUSI
A1: Fornitori ESCLUSI dalla cassa per scelta (is_excluded) — fuori dal saldo proiettato. NON sono un TODO: il motivo è in colonna Motivo.
A2: Cod | B2: Nome (da CSV) | C2: GENNAIO | D2: FEBBRAIO | E2: MARZO | F2: APRILE | G2: MAGGIO | H2: GIUGNO | I2: LUGLIO | J2: AGOSTO | K2: SETTEMBRE | L2: OTTOBRE | M2: NOVEMBRE | N2: DICEMBRE | O2: Motivo
A3: 1033 | B3: EURO GROUP NETWORK S.R.L. | G3: 31.99 | O3: una_tantum
A4: 1048 | B4: MEDITERRANEO SNC DI TRAMONTANO | G4: 59.99 | O4: una_tantum
A5: 264 | B5: PANORAMA COMPANY S.R.L. | G5: 412036.53 | O5: intercompany
A6: 796 | B6: RAIA LIBERATO | G6: 66.01 | O6: una_tantum
A7: 236 | B7: RISTORANTE GIARDINIELLO SRL | G7: 97.5 | O7: una_tantum
A8: 85 | B8: TECNO CAMPANIA SRL | G8: 63440 | O8: una_tantum

Sheet DA MAPPARE1
A1: Fornitori NON mappati in d_fornitori.csv — assegnare una voce (hotelops fornitori) e rigenerare
A2: Cod | B2: Nome (da export) | C2: GENNAIO | D2: FEBBRAIO | E2: MARZO | F2: APRILE | G2: MAGGIO | H2: GIUGNO | I2: LUGLIO | J2: AGOSTO | K2: SETTEMBRE | L2: OTTOBRE | M2: NOVEMBRE | N2: DICEMBRE

Sheet ESCLUSI1
A1: Fornitori ESCLUSI dalla cassa per scelta (is_excluded) — fuori dal saldo proiettato. NON sono un TODO: il motivo è in colonna Motivo.
A2: Cod | B2: Nome (da CSV) | C2: GENNAIO | D2: FEBBRAIO | E2: MARZO | F2: APRILE | G2: MAGGIO | H2: GIUGNO | I2: LUGLIO | J2: AGOSTO | K2: SETTEMBRE | L2: OTTOBRE | M2: NOVEMBRE | N2: DICEMBRE | O2: Motivo
A3: 1033 | B3: EURO GROUP NETWORK S.R.L. | H3: 31.99 | O3: una_tantum
A4: 1048 | B4: MEDITERRANEO SNC DI TRAMONTANO | H4: 59.99 | O4: una_tantum
A5: 264 | B5: PANORAMA COMPANY S.R.L. | H5: 412036.53 | O5: intercompany
A6: 796 | B6: RAIA LIBERATO | H6: 66.01 | O6: una_tantum
A7: 236 | B7: RISTORANTE GIARDINIELLO SRL | H7: 97.5 | O7: una_tantum
A8: 85 | B8: TECNO CAMPANIA SRL | H8: 63440 | O8: una_tantum

Sheet DA MAPPARE2
A1: Fornitori NON mappati in d_fornitori.csv — assegnare una voce (hotelops fornitori) e rigenerare
A2: Cod | B2: Nome (da export) | C2: GENNAIO | D2: FEBBRAIO | E2: MARZO | F2: APRILE | G2: MAGGIO | H2: GIUGNO | I2: LUGLIO | J2: AGOSTO | K2: SETTEMBRE | L2: OTTOBRE | M2: NOVEMBRE | N2: DICEMBRE
A3: 671 | B3: 2A SYSTEMS SRL | I3: 220
A4: 722 | B4: Barbella Srl | I4: 939.4
A5: 1819 | B5: FUEL STATION SRL | I5: 120
A6: 1795 | B6: HYGIEN TECH S.R.L. | I6: 1365.83
A7: 1078 | B7: Intesa Sanpaolo S.p.a | I7: 67.1
A8: 414 | B8: NEXI PAYMENTS S.p.A. | I8: 25.44

Sheet ESCLUSI2
A1: Fornitori ESCLUSI dalla cassa per scelta (is_excluded) — fuori dal saldo proiettato. NON sono un TODO: il motivo è in colonna Motivo.
A2: Cod | B2: Nome (da CSV) | C2: GENNAIO | D2: FEBBRAIO | E2: MARZO | F2: APRILE | G2: MAGGIO | H2: GIUGNO | I2: LUGLIO | J2: AGOSTO | K2: SETTEMBRE | L2: OTTOBRE | M2: NOVEMBRE | N2: DICEMBRE | O2: Motivo
A3: 1033 | B3: EURO GROUP NETWORK S.R.L. | I3: 31.99 | O3: una_tantum
A4: 1048 | B4: MEDITERRANEO SNC DI TRAMONTANO | I4: 59.99 | O4: una_tantum
A5: 264 | B5: PANORAMA COMPANY S.R.L. | I5: 412036.53 | O5: intercompany
A6: 796 | B6: RAIA LIBERATO | I6: 66.01 | O6: una_tantum
A7: 236 | B7: RISTORANTE GIARDINIELLO SRL | I7: 97.5 | O7: una_tantum
A8: 85 | B8: TECNO CAMPANIA SRL | I8: 45440 | O8: una_tantum

Sheet DA MAPPARE3
A1: Fornitori NON mappati in d_fornitori.csv — assegnare una voce (hotelops fornitori) e rigenerare
A2: Cod | B2: Nome (da export) | C2: GENNAIO | D2: FEBBRAIO | E2: MARZO | F2: APRILE | G2: MAGGIO | H2: GIUGNO | I2: LUGLIO | J2: AGOSTO | K2: SETTEMBRE | L2: OTTOBRE | M2: NOVEMBRE | N2: DICEMBRE

Sheet ESCLUSI3
A1: Fornitori ESCLUSI dalla cassa per scelta (is_excluded) — fuori dal saldo proiettato. NON sono un TODO: il motivo è in colonna Motivo.
A2: Cod | B2: Nome (da CSV) | C2: GENNAIO | D2: FEBBRAIO | E2: MARZO | F2: APRILE | G2: MAGGIO | H2: GIUGNO | I2: LUGLIO | J2: AGOSTO | K2: SETTEMBRE | L2: OTTOBRE | M2: NOVEMBRE | N2: DICEMBRE | O2: Motivo
A3: 1048 | B3: MEDITERRANEO SNC DI TRAMONTANO | J3: 59.99 | O3: una_tantum
A4: 264 | B4: PANORAMA COMPANY S.R.L. | J4: 412036.53 | O4: intercompany
A5: 236 | B5: RISTORANTE GIARDINIELLO SRL | J5: 97.5 | O5: una_tantum

Sheet DA MAPPARE4
A1: Fornitori NON mappati in d_fornitori.csv — assegnare una voce (hotelops fornitori) e rigenerare
A2: Cod | B2: Nome (da export) | C2: GENNAIO | D2: FEBBRAIO | E2: MARZO | F2: APRILE | G2: MAGGIO | H2: GIUGNO | I2: LUGLIO | J2: AGOSTO | K2: SETTEMBRE | L2: OTTOBRE | M2: NOVEMBRE | N2: DICEMBRE
A3: 671 | B3: 2A SYSTEMS SRL | K3: 220
A4: 722 | B4: Barbella Srl | K4: 939.4
A5: 654 | B5: GOOGLE CLOUD ITALY S.R.L. | K5: 205.4
A6: 921 | B6: IL CENTRO C.S.C. SRL | K6: 688.2
A7: 1911 | B7: Masucci Marco | K7: 761.28
A8: 414 | B8: NEXI PAYMENTS S.p.A. | K8: 12.81
A9: 1890 | B9: Tsemplifico soc. coop. | K9: 1830

Sheet ESCLUSI4
A1: Fornitori ESCLUSI dalla cassa per scelta (is_excluded) — fuori dal saldo proiettato. NON sono un TODO: il motivo è in colonna Motivo.
A2: Cod | B2: Nome (da CSV) | C2: GENNAIO | D2: FEBBRAIO | E2: MARZO | F2: APRILE | G2: MAGGIO | H2: GIUGNO | I2: LUGLIO | J2: AGOSTO | K2: SETTEMBRE | L2: OTTOBRE | M2: NOVEMBRE | N2: DICEMBRE | O2: Motivo
A3: 1033 | B3: EURO GROUP NETWORK S.R.L. | K3: 31.99 | O3: una_tantum
A4: 1048 | B4: MEDITERRANEO SNC DI TRAMONTANO | K4: 59.99 | O4: una_tantum
A5: 264 | B5: PANORAMA COMPANY S.R.L. | K5: 412036.53 | O5: intercompany
A6: 796 | B6: RAIA LIBERATO | K6: 66.01 | O6: una_tantum
A7: 236 | B7: RISTORANTE GIARDINIELLO SRL | K7: 97.5 | O7: una_tantum
A8: 85 | B8: TECNO CAMPANIA SRL | K8: 45440 | O8: una_tantum
